{
  "school_id": 1353,
  "name": "浙江工商职业技术学院",
  "level": "专科（高职）",
  "is_985": false,
  "is_211": false,
  "dual_class": "",
  "city": "宁波市",
  "province": "浙江",
  "type": "财经类",
  "nature": "公办",
  "province_scores": [
    {
      "admissions": "2",
      "answerurl": "",
      "average": "-",
      "avg_section": "-",
      "city_name": "宁波市",
      "county_name": "",
      "diff": "-",
      "doublehigh": "0",
      "dual_class": 38003,
      "dual_class_name": "",
      "f211": 2,
      "f985": 2,
      "filing": 0,
      "first_km": 0,
      "level_name": "专科（高职）",
      "local_batch_id": "10",
      "local_batch_name": "专科批",
      "local_province_name": "河南",
      "local_type_name": "文科",
      "major_score": "-",
      "max": "-",
      "min": 457,
      "min_section": 108390,
      "name": "浙江工商职业技术学院",
      "nature_name": "公办",
      "num": "-",
      "proscore": "-",
      "province_id": 33,
      "province_name": "浙江",
      "school_id": 1353,
      "sg_fxk": 0,
      "sg_info": "",
      "sg_name": "",
      "sg_sxk": "",
      "sg_type": 0,
      "special_group": "0",
      "type_name": "财经类",
      "xclevel_name": "",
      "year": 2023,
      "zslx_name": "普通类",
      "data_type": "province"
    },
    {
      "admissions": "2",
      "answerurl": "",
      "average": "-",
      "avg_section": "-",
      "city_name": "宁波市",
      "county_name": "",
      "diff": "-",
      "doublehigh": "0",
      "dual_class": 38003,
      "dual_class_name": "",
      "f211": 2,
      "f985": 2,
      "filing": 0,
      "first_km": 0,
      "level_name": "专科（高职）",
      "local_batch_id": "10",
      "local_batch_name": "专科批",
      "local_province_name": "河南",
      "local_type_name": "理科",
      "major_score": "-",
      "max": "-",
      "min": 410,
      "min_section": 318459,
      "name": "浙江工商职业技术学院",
      "nature_name": "公办",
      "num": "-",
      "proscore": "-",
      "province_id": 33,
      "province_name": "浙江",
      "school_id": 1353,
      "sg_fxk": 0,
      "sg_info": "",
      "sg_name": "",
      "sg_sxk": "",
      "sg_type": 0,
      "special_group": "0",
      "type_name": "财经类",
      "xclevel_name": "",
      "year": 2023,
      "zslx_name": "普通类",
      "data_type": "province"
    },
    {
      "admissions": "2",
      "answerurl": "",
      "average": "-",
      "avg_section": "-",
      "city_name": "宁波市",
      "county_name": "",
      "diff": 207,
      "doublehigh": "0",
      "dual_class": 38003,
      "dual_class_name": "",
      "f211": 2,
      "f985": 2,
      "filing": 0,
      "first_km": 0,
      "level_name": "专科（高职）",
      "local_batch_id": "10",
      "local_batch_name": "专科批",
      "local_province_name": "河南",
      "local_type_name": "理科",
      "major_score": "-",
      "max": "-",
      "min": 392,
      "min_section": 336443,
      "name": "浙江工商职业技术学院",
      "nature_name": "公办",
      "num": 16,
      "proscore": 185,
      "province_id": 33,
      "province_name": "浙江",
      "school_id": 1353,
      "sg_fxk": 0,
      "sg_info": "",
      "sg_name": "",
      "sg_sxk": "",
      "sg_type": 0,
      "special_group": "0",
      "type_name": "财经类",
      "xclevel_name": "",
      "year": 2024,
      "zslx_name": "普通类",
      "data_type": "province"
    },
    {
      "admissions": "2",
      "answerurl": "",
      "average": "-",
      "avg_section": "-",
      "city_name": "宁波市",
      "county_name": "",
      "diff": 205,
      "doublehigh": "0",
      "dual_class": 38003,
      "dual_class_name": "",
      "f211": 2,
      "f985": 2,
      "filing": 0,
      "first_km": 0,
      "level_name": "专科（高职）",
      "local_batch_id": "10",
      "local_batch_name": "专科批",
      "local_province_name": "河南",
      "local_type_name": "文科",
      "major_score": "-",
      "max": "-",
      "min": 390,
      "min_section": 136143,
      "name": "浙江工商职业技术学院",
      "nature_name": "公办",
      "num": 14,
      "proscore": 185,
      "province_id": 33,
      "province_name": "浙江",
      "school_id": 1353,
      "sg_fxk": 0,
      "sg_info": "",
      "sg_name": "",
      "sg_sxk": "",
      "sg_type": 0,
      "special_group": "0",
      "type_name": "财经类",
      "xclevel_name": "",
      "year": 2024,
      "zslx_name": "普通类",
      "data_type": "province"
    },
    {
      "admissions": "2",
      "answerurl": "",
      "average": 469,
      "avg_section": "-",
      "city_name": "宁波市",
      "county_name": "",
      "diff": 277,
      "doublehigh": "0",
      "dual_class": 38003,
      "dual_class_name": "",
      "f211": 2,
      "f985": 2,
      "filing": 0,
      "first_km": 70004,
      "level_name": "专科（高职）",
      "local_batch_id": "10",
      "local_batch_name": "专科批",
      "local_province_name": "河南",
      "local_type_name": "历史类",
      "major_score": "-",
      "max": 491,
      "min": 462,
      "min_section": 99501,
      "name": "浙江工商职业技术学院",
      "nature_name": "公办",
      "num": 20,
      "proscore": 185,
      "province_id": 33,
      "province_name": "浙江",
      "school_id": 1353,
      "sg_fxk": 70004,
      "sg_info": "首选历史，再选不限",
      "sg_name": "（101）",
      "sg_sxk": "70008",
      "sg_type": 80001,
      "special_group": "504555",
      "type_name": "财经类",
      "xclevel_name": "",
      "year": 2025,
      "zslx_name": "普通类",
      "data_type": "province"
    },
    {
      "admissions": "2",
      "answerurl": "",
      "average": 439,
      "avg_section": "-",
      "city_name": "宁波市",
      "county_name": "",
      "diff": 245,
      "doublehigh": "0",
      "dual_class": 38003,
      "dual_class_name": "",
      "f211": 2,
      "f985": 2,
      "filing": 0,
      "first_km": 70000,
      "level_name": "专科（高职）",
      "local_batch_id": "10",
      "local_batch_name": "专科批",
      "local_province_name": "河南",
      "local_type_name": "物理类",
      "major_score": "-",
      "max": 459,
      "min": 430,
      "min_section": 342982,
      "name": "浙江工商职业技术学院",
      "nature_name": "公办",
      "num": 20,
      "proscore": 185,
      "province_id": 33,
      "province_name": "浙江",
      "school_id": 1353,
      "sg_fxk": 70000,
      "sg_info": "首选物理，再选不限",
      "sg_name": "（102）",
      "sg_sxk": "70008",
      "sg_type": 80001,
      "special_group": "504566",
      "type_name": "财经类",
      "xclevel_name": "",
      "year": 2025,
      "zslx_name": "普通类",
      "data_type": "province"
    }
  ],
  "special_scores": [
    {
      "average": 465,
      "doublehigh": 0,
      "dual_class_name": "",
      "first_km": 0,
      "id": "gkspecialscore2023781851",
      "info": "",
      "is_score_range": 2,
      "is_top": 2,
      "level2_name": "财经商贸大类",
      "level3_name": "财务会计类",
      "local_batch_name": "专科批",
      "local_province_name": "河南",
      "local_type_name": "文科",
      "max": 465,
      "min": 465,
      "min_range": "",
      "min_rank_range": "",
      "min_section": 99108,
      "name": "浙江工商职业技术学院",
      "proscore": 185,
      "remark": "",
      "school_id": 1353,
      "sg_fxk": "",
      "sg_info": "",
      "sg_name": "",
      "sg_sxk": "",
      "sg_type": 0,
      "single": "75006",
      "sp_fxk": "",
      "sp_info": "",
      "sp_name": "大数据与会计",
      "sp_scode": "04",
      "sp_sxk": "",
      "sp_type": 0,
      "spe_id": 9085,
      "special_group": 0,
      "special_id": 1593453,
      "spname": "大数据与会计",
      "year": 2023,
      "zslx_name": "-",
      "data_type": "special"
    },
    {
      "average": 463,
      "doublehigh": 0,
      "dual_class_name": "",
      "first_km": 0,
      "id": "gkspecialscore2023781856",
      "info": "",
      "is_score_range": 2,
      "is_top": 2,
      "level2_name": "教育与体育大类",
      "level3_name": "语言类",
      "local_batch_name": "专科批",
      "local_province_name": "河南",
      "local_type_name": "文科",
      "max": 463,
      "min": 463,
      "min_range": "",
      "min_rank_range": "",
      "min_section": 101517,
      "name": "浙江工商职业技术学院",
      "proscore": 185,
      "remark": "",
      "school_id": 1353,
      "sg_fxk": "",
      "sg_info": "",
      "sg_name": "",
      "sg_sxk": "",
      "sg_type": 0,
      "single": "75006",
      "sp_fxk": "",
      "sp_info": "",
      "sp_name": "应用英语",
      "sp_scode": "09",
      "sp_sxk": "",
      "sp_type": 0,
      "spe_id": 1012,
      "special_group": 0,
      "special_id": 53602,
      "spname": "应用英语",
      "year": 2023,
      "zslx_name": "-",
      "data_type": "special"
    },
    {
      "average": 461,
      "doublehigh": 0,
      "dual_class_name": "",
      "first_km": 0,
      "id": "gkspecialscore2023781849",
      "info": "（第一学年在宁波本部校区，第二学年起在慈溪校区）",
      "is_score_range": 2,
      "is_top": 2,
      "level2_name": "装备制造大类",
      "level3_name": "自动化类",
      "local_batch_name": "专科批",
      "local_province_name": "河南",
      "local_type_name": "文科",
      "max": 461,
      "min": 461,
      "min_range": "",
      "min_rank_range": "",
      "min_section": 103791,
      "name": "浙江工商职业技术学院",
      "proscore": 185,
      "remark": "",
      "school_id": 1353,
      "sg_fxk": "",
      "sg_info": "",
      "sg_name": "",
      "sg_sxk": "",
      "sg_type": 0,
      "single": "75006",
      "sp_fxk": "",
      "sp_info": "",
      "sp_name": "工业机器人技术",
      "sp_scode": "02",
      "sp_sxk": "",
      "sp_type": 0,
      "spe_id": 600,
      "special_group": 0,
      "special_id": 1375942,
      "spname": "工业机器人技术（第一学年在宁波本部校区，第二学年起在慈溪校区）",
      "year": 2023,
      "zslx_name": "-",
      "data_type": "special"
    },
    {
      "average": 459,
      "doublehigh": 0,
      "dual_class_name": "",
      "first_km": 0,
      "id": "gkspecialscore2023781854",
      "info": "",
      "is_score_range": 2,
      "is_top": 2,
      "level2_name": "财经商贸大类",
      "level3_name": "电子商务类",
      "local_batch_name": "专科批",
      "local_province_name": "河南",
      "local_type_name": "文科",
      "max": 460,
      "min": 459,
      "min_range": "",
      "min_rank_range": "",
      "min_section": 106020,
      "name": "浙江工商职业技术学院",
      "proscore": 185,
      "remark": "",
      "school_id": 1353,
      "sg_fxk": "",
      "sg_info": "",
      "sg_name": "",
      "sg_sxk": "",
      "sg_type": 0,
      "single": "75006",
      "sp_fxk": "",
      "sp_info": "",
      "sp_name": "跨境电子商务",
      "sp_scode": "07",
      "sp_sxk": "",
      "sp_type": 0,
      "spe_id": 1982,
      "special_group": 0,
      "special_id": 1359199,
      "spname": "跨境电子商务",
      "year": 2023,
      "zslx_name": "-",
      "data_type": "special"
    },
    {
      "average": 460,
      "doublehigh": 0,
      "dual_class_name": "",
      "first_km": 0,
      "id": "gkspecialscore2023781852",
      "info": "",
      "is_score_range": 2,
      "is_top": 2,
      "level2_name": "财经商贸大类",
      "level3_name": "经济贸易类",
      "local_batch_name": "专科批",
      "local_province_name": "河南",
      "local_type_name": "文科",
      "max": 461,
      "min": 459,
      "min_range": "",
      "min_rank_range": "",
      "min_section": 106020,
      "name": "浙江工商职业技术学院",
      "proscore": 185,
      "remark": "",
      "school_id": 1353,
      "sg_fxk": "",
      "sg_info": "",
      "sg_name": "",
      "sg_sxk": "",
      "sg_type": 0,
      "single": "75006",
      "sp_fxk": "",
      "sp_info": "",
      "sp_name": "关务与外贸服务",
      "sp_scode": "05",
      "sp_sxk": "",
      "sp_type": 0,
      "spe_id": 9089,
      "special_group": 0,
      "special_id": 1597955,
      "spname": "关务与外贸服务",
      "year": 2023,
      "zslx_name": "-",
      "data_type": "special"
    },
    {
      "average": 459,
      "doublehigh": 0,
      "dual_class_name": "",
      "first_km": 0,
      "id": "gkspecialscore2023781850",
      "info": "（第一学年在宁波本部校区，第二学年起在慈溪校区）",
      "is_score_range": 2,
      "is_top": 2,
      "level2_name": "装备制造大类",
      "level3_name": "自动化类",
      "local_batch_name": "专科批",
      "local_province_name": "河南",
      "local_type_name": "文科",
      "max": 459,
      "min": 459,
      "min_range": "",
      "min_rank_range": "",
      "min_section": 106020,
      "name": "浙江工商职业技术学院",
      "proscore": 185,
      "remark": "",
      "school_id": 1353,
      "sg_fxk": "",
      "sg_info": "",
      "sg_name": "",
      "sg_sxk": "",
      "sg_type": 0,
      "single": "75006",
      "sp_fxk": "",
      "sp_info": "",
      "sp_name": "电气自动化技术",
      "sp_scode": "03",
      "sp_sxk": "",
      "sp_type": 0,
      "spe_id": 593,
      "special_group": 0,
      "special_id": 53587,
      "spname": "电气自动化技术（第一学年在宁波本部校区，第二学年起在慈溪校区）",
      "year": 2023,
      "zslx_name": "-",
      "data_type": "special"
    },
    {
      "average": 459,
      "doublehigh": 0,
      "dual_class_name": "",
      "first_km": 0,
      "id": "gkspecialscore2023781848",
      "info": "",
      "is_score_range": 2,
      "is_top": 2,
      "level2_name": "土木建筑大类",
      "level3_name": "土建施工类",
      "local_batch_name": "专科批",
      "local_province_name": "河南",
      "local_type_name": "文科",
      "max": 459,
      "min": 459,
      "min_range": "",
      "min_rank_range": "",
      "min_section": 106020,
      "name": "浙江工商职业技术学院",
      "proscore": 185,
      "remark": "",
      "school_id": 1353,
      "sg_fxk": "",
      "sg_info": "",
      "sg_name": "",
      "sg_sxk": "",
      "sg_type": 0,
      "single": "75006",
      "sp_fxk": "",
      "sp_info": "",
      "sp_name": "建筑工程技术",
      "sp_scode": "01",
      "sp_sxk": "",
      "sp_type": 0,
      "spe_id": 528,
      "special_group": 0,
      "special_id": 53570,
      "spname": "建筑工程技术",
      "year": 2023,
      "zslx_name": "-",
      "data_type": "special"
    },
    {
      "average": 461,
      "doublehigh": 0,
      "dual_class_name": "",
      "first_km": 0,
      "id": "gkspecialscore2023781855",
      "info": "",
      "is_score_range": 2,
      "is_top": 2,
      "level2_name": "旅游大类",
      "level3_name": "旅游类",
      "local_batch_name": "专科批",
      "local_province_name": "河南",
      "local_type_name": "文科",
      "max": 465,
      "min": 458,
      "min_range": "",
      "min_rank_range": "",
      "min_section": 107202,
      "name": "浙江工商职业技术学院",
      "proscore": 185,
      "remark": "",
      "school_id": 1353,
      "sg_fxk": "",
      "sg_info": "",
      "sg_name": "",
      "sg_sxk": "",
      "sg_type": 0,
      "single": "75006",
      "sp_fxk": "",
      "sp_info": "",
      "sp_name": "旅游管理",
      "sp_scode": "08",
      "sp_sxk": "",
      "sp_type": 0,
      "spe_id": 896,
      "special_group": 0,
      "special_id": 53573,
      "spname": "旅游管理",
      "year": 2023,
      "zslx_name": "-",
      "data_type": "special"
    },
    {
      "average": 457,
      "doublehigh": 0,
      "dual_class_name": "",
      "first_km": 0,
      "id": "gkspecialscore2023781853",
      "info": "",
      "is_score_range": 2,
      "is_top": 2,
      "level2_name": "财经商贸大类",
      "level3_name": "工商管理类",
      "local_batch_name": "专科批",
      "local_province_name": "河南",
      "local_type_name": "文科",
      "max": 457,
      "min": 457,
      "min_range": "",
      "min_rank_range": "",
      "min_section": 108390,
      "name": "浙江工商职业技术学院",
      "proscore": 185,
      "remark": "",
      "school_id": 1353,
      "sg_fxk": "",
      "sg_info": "",
      "sg_name": "",
      "sg_sxk": "",
      "sg_type": 0,
      "single": "75006",
      "sp_fxk": "",
      "sp_info": "",
      "sp_name": "市场营销",
      "sp_scode": "06",
      "sp_sxk": "",
      "sp_type": 0,
      "spe_id": 882,
      "special_group": 0,
      "special_id": 53577,
      "spname": "市场营销",
      "year": 2023,
      "zslx_name": "-",
      "data_type": "special"
    },
    {
      "average": 430,
      "doublehigh": 0,
      "dual_class_name": "",
      "first_km": 0,
      "id": "gkspecialscore2023784148",
      "info": "（第一学年在宁波本部校区，第二学年起在宁海校区）",
      "is_score_range": 2,
      "is_top": 2,
      "level2_name": "装备制造大类",
      "level3_name": "自动化类",
      "local_batch_name": "专科批",
      "local_province_name": "河南",
      "local_type_name": "理科",
      "max": 476,
      "min": 412,
      "min_range": "",
      "min_rank_range": "",
      "min_section": 314815,
      "name": "浙江工商职业技术学院",
      "proscore": 185,
      "remark": "",
      "school_id": 1353,
      "sg_fxk": "",
      "sg_info": "",
      "sg_name": "",
      "sg_sxk": "",
      "sg_type": 0,
      "single": "75006",
      "sp_fxk": "",
      "sp_info": "",
      "sp_name": "机电一体化技术",
      "sp_scode": "03",
      "sp_sxk": "",
      "sp_type": 0,
      "spe_id": 592,
      "special_group": 0,
      "special_id": 53588,
      "spname": "机电一体化技术（第一学年在宁波本部校区，第二学年起在宁海校区）",
      "year": 2023,
      "zslx_name": "-",
      "data_type": "special"
    },
    {
      "average": 415,
      "doublehigh": 0,
      "dual_class_name": "",
      "first_km": 0,
      "id": "gkspecialscore2023784147",
      "info": "（第一学年在宁波本部校区，第二学年起在宁海校区）",
      "is_score_range": 2,
      "is_top": 2,
      "level2_name": "装备制造大类",
      "level3_name": "机械设计制造类",
      "local_batch_name": "专科批",
      "local_province_name": "河南",
      "local_type_name": "理科",
      "max": 418,
      "min": 412,
      "min_range": "",
      "min_rank_range": "",
      "min_section": 314815,
      "name": "浙江工商职业技术学院",
      "proscore": 185,
      "remark": "",
      "school_id": 1353,
      "sg_fxk": "",
      "sg_info": "",
      "sg_name": "",
      "sg_sxk": "",
      "sg_type": 0,
      "single": "75006",
      "sp_fxk": "",
      "sp_info": "",
      "sp_name": "模具设计与制造",
      "sp_scode": "02",
      "sp_sxk": "",
      "sp_type": 0,
      "spe_id": 578,
      "special_group": 0,
      "special_id": 53571,
      "spname": "模具设计与制造（第一学年在宁波本部校区，第二学年起在宁海校区）",
      "year": 2023,
      "zslx_name": "-",
      "data_type": "special"
    },
    {
      "average": 412,
      "doublehigh": 0,
      "dual_class_name": "",
      "first_km": 0,
      "id": "gkspecialscore2023784146",
      "info": "",
      "is_score_range": 2,
      "is_top": 2,
      "level2_name": "土木建筑大类",
      "level3_name": "土建施工类",
      "local_batch_name": "专科批",
      "local_province_name": "河南",
      "local_type_name": "理科",
      "max": 412,
      "min": 412,
      "min_range": "",
      "min_rank_range": "",
      "min_section": 314815,
      "name": "浙江工商职业技术学院",
      "proscore": 185,
      "remark": "",
      "school_id": 1353,
      "sg_fxk": "",
      "sg_info": "",
      "sg_name": "",
      "sg_sxk": "",
      "sg_type": 0,
      "single": "75006",
      "sp_fxk": "",
      "sp_info": "",
      "sp_name": "建筑工程技术",
      "sp_scode": "01",
      "sp_sxk": "",
      "sp_type": 0,
      "spe_id": 528,
      "special_group": 0,
      "special_id": 53570,
      "spname": "建筑工程技术",
      "year": 2023,
      "zslx_name": "-",
      "data_type": "special"
    },
    {
      "average": 414,
      "doublehigh": 0,
      "dual_class_name": "",
      "first_km": 0,
      "id": "gkspecialscore2023784151",
      "info": "（第一学年在宁波本部校区，第二学年起在慈溪校区）",
      "is_score_range": 2,
      "is_top": 2,
      "level2_name": "电子与信息大类",
      "level3_name": "电子信息类",
      "local_batch_name": "专科批",
      "local_province_name": "河南",
      "local_type_name": "理科",
      "max": 418,
      "min": 411,
      "min_range": "",
      "min_rank_range": "",
      "min_section": 316583,
      "name": "浙江工商职业技术学院",
      "proscore": 185,
      "remark": "",
      "school_id": 1353,
      "sg_fxk": "",
      "sg_info": "",
      "sg_name": "",
      "sg_sxk": "",
      "sg_type": 0,
      "single": "75006",
      "sp_fxk": "",
      "sp_info": "",
      "sp_name": "应用电子技术",
      "sp_scode": "06",
      "sp_sxk": "",
      "sp_type": 0,
      "spe_id": 765,
      "special_group": 0,
      "special_id": 53586,
      "spname": "应用电子技术（第一学年在宁波本部校区，第二学年起在慈溪校区）",
      "year": 2023,
      "zslx_name": "-",
      "data_type": "special"
    },
    {
      "average": 415,
      "doublehigh": 0,
      "dual_class_name": "",
      "first_km": 0,
      "id": "gkspecialscore2023784150",
      "info": "（第一学年在宁波本部校区，第二学年起在慈溪校区）",
      "is_score_range": 2,
      "is_top": 2,
      "level2_name": "装备制造大类",
      "level3_name": "自动化类",
      "local_batch_name": "专科批",
      "local_province_name": "河南",
      "local_type_name": "理科",
      "max": 419,
      "min": 411,
      "min_range": "",
      "min_rank_range": "",
      "min_section": 316583,
      "name": "浙江工商职业技术学院",
      "proscore": 185,
      "remark": "",
      "school_id": 1353,
      "sg_fxk": "",
      "sg_info": "",
      "sg_name": "",
      "sg_sxk": "",
      "sg_type": 0,
      "single": "75006",
      "sp_fxk": "",
      "sp_info": "",
      "sp_name": "电气自动化技术",
      "sp_scode": "05",
      "sp_sxk": "",
      "sp_type": 0,
      "spe_id": 593,
      "special_group": 0,
      "special_id": 53587,
      "spname": "电气自动化技术（第一学年在宁波本部校区，第二学年起在慈溪校区）",
      "year": 2023,
      "zslx_name": "-",
      "data_type": "special"
    },
    {
      "average": 410,
      "doublehigh": 0,
      "dual_class_name": "",
      "first_km": 0,
      "id": "gkspecialscore2023784149",
      "info": "（第一学年在宁波本部校区，第二学年起在慈溪校区）",
      "is_score_range": 2,
      "is_top": 2,
      "level2_name": "装备制造大类",
      "level3_name": "自动化类",
      "local_batch_name": "专科批",
      "local_province_name": "河南",
      "local_type_name": "理科",
      "max": 411,
      "min": 410,
      "min_range": "",
      "min_rank_range": "",
      "min_section": 318459,
      "name": "浙江工商职业技术学院",
      "proscore": 185,
      "remark": "",
      "school_id": 1353,
      "sg_fxk": "",
      "sg_info": "",
      "sg_name": "",
      "sg_sxk": "",
      "sg_type": 0,
      "single": "75006",
      "sp_fxk": "",
      "sp_info": "",
      "sp_name": "工业机器人技术",
      "sp_scode": "04",
      "sp_sxk": "",
      "sp_type": 0,
      "spe_id": 600,
      "special_group": 0,
      "special_id": 1375942,
      "spname": "工业机器人技术（第一学年在宁波本部校区，第二学年起在慈溪校区）",
      "year": 2023,
      "zslx_name": "-",
      "data_type": "special"
    },
    {
      "average": 425,
      "doublehigh": 0,
      "dual_class_name": "",
      "first_km": 0,
      "id": "gkspecialscore20241300227",
      "info": "",
      "is_score_range": 2,
      "is_top": 2,
      "level2_name": "财经商贸大类",
      "level3_name": "财务会计类",
      "local_batch_name": "专科批",
      "local_province_name": "河南",
      "local_type_name": "文科",
      "max": 425,
      "min": 425,
      "min_range": "",
      "min_rank_range": "",
      "min_section": 100480,
      "name": "浙江工商职业技术学院",
      "proscore": 185,
      "remark": "",
      "school_id": 1353,
      "sg_fxk": "",
      "sg_info": "",
      "sg_name": "",
      "sg_sxk": "",
      "sg_type": 0,
      "single": "75006",
      "sp_fxk": "",
      "sp_info": "",
      "sp_name": "大数据与会计",
      "sp_scode": "03",
      "sp_sxk": "",
      "sp_type": 0,
      "spe_id": 9085,
      "special_group": 0,
      "special_id": 1593453,
      "spname": "大数据与会计",
      "year": 2024,
      "zslx_name": "-",
      "data_type": "special"
    },
    {
      "average": 423,
      "doublehigh": 0,
      "dual_class_name": "",
      "first_km": 0,
      "id": "gkspecialscore20241300230",
      "info": "",
      "is_score_range": 2,
      "is_top": 2,
      "level2_name": "财经商贸大类",
      "level3_name": "电子商务类",
      "local_batch_name": "专科批",
      "local_province_name": "河南",
      "local_type_name": "文科",
      "max": 427,
      "min": 418,
      "min_range": "",
      "min_rank_range": "",
      "min_section": 107145,
      "name": "浙江工商职业技术学院",
      "proscore": 185,
      "remark": "",
      "school_id": 1353,
      "sg_fxk": "",
      "sg_info": "",
      "sg_name": "",
      "sg_sxk": "",
      "sg_type": 0,
      "single": "75006",
      "sp_fxk": "",
      "sp_info": "",
      "sp_name": "电子商务",
      "sp_scode": "06",
      "sp_sxk": "",
      "sp_type": 0,
      "spe_id": 886,
      "special_group": 0,
      "special_id": 53576,
      "spname": "电子商务",
      "year": 2024,
      "zslx_name": "-",
      "data_type": "special"
    },
    {
      "average": 419,
      "doublehigh": 0,
      "dual_class_name": "",
      "first_km": 0,
      "id": "gkspecialscore20241300233",
      "info": "",
      "is_score_range": 2,
      "is_top": 2,
      "level2_name": "教育与体育大类",
      "level3_name": "语言类",
      "local_batch_name": "专科批",
      "local_province_name": "河南",
      "local_type_name": "文科",
      "max": 425,
      "min": 411,
      "min_range": "",
      "min_rank_range": "",
      "min_section": 113991,
      "name": "浙江工商职业技术学院",
      "proscore": 185,
      "remark": "",
      "school_id": 1353,
      "sg_fxk": "",
      "sg_info": "",
      "sg_name": "",
      "sg_sxk": "",
      "sg_type": 0,
      "single": "75006",
      "sp_fxk": "",
      "sp_info": "",
      "sp_name": "应用英语",
      "sp_scode": "09",
      "sp_sxk": "",
      "sp_type": 0,
      "spe_id": 1012,
      "special_group": 0,
      "special_id": 53602,
      "spname": "应用英语",
      "year": 2024,
      "zslx_name": "-",
      "data_type": "special"
    },
    {
      "average": 411,
      "doublehigh": 0,
      "dual_class_name": "",
      "first_km": 0,
      "id": "gkspecialscore20241300229",
      "info": "",
      "is_score_range": 2,
      "is_top": 2,
      "level2_name": "财经商贸大类",
      "level3_name": "工商管理类",
      "local_batch_name": "专科批",
      "local_province_name": "河南",
      "local_type_name": "文科",
      "max": 411,
      "min": 411,
      "min_range": "",
      "min_rank_range": "",
      "min_section": 113991,
      "name": "浙江工商职业技术学院",
      "proscore": 185,
      "remark": "",
      "school_id": 1353,
      "sg_fxk": "",
      "sg_info": "",
      "sg_name": "",
      "sg_sxk": "",
      "sg_type": 0,
      "single": "75006",
      "sp_fxk": "",
      "sp_info": "",
      "sp_name": "市场营销",
      "sp_scode": "05",
      "sp_sxk": "",
      "sp_type": 0,
      "spe_id": 882,
      "special_group": 0,
      "special_id": 53577,
      "spname": "市场营销",
      "year": 2024,
      "zslx_name": "-",
      "data_type": "special"
    },
    {
      "average": 411,
      "doublehigh": 0,
      "dual_class_name": "",
      "first_km": 0,
      "id": "gkspecialscore20241300225",
      "info": "",
      "is_score_range": 2,
      "is_top": 2,
      "level2_name": "土木建筑大类",
      "level3_name": "土建施工类",
      "local_batch_name": "专科批",
      "local_province_name": "河南",
      "local_type_name": "文科",
      "max": 411,
      "min": 411,
      "min_range": "",
      "min_rank_range": "",
      "min_section": 113991,
      "name": "浙江工商职业技术学院",
      "proscore": 185,
      "remark": "",
      "school_id": 1353,
      "sg_fxk": "",
      "sg_info": "",
      "sg_name": "",
      "sg_sxk": "",
      "sg_type": 0,
      "single": "75006",
      "sp_fxk": "",
      "sp_info": "",
      "sp_name": "建筑工程技术",
      "sp_scode": "01",
      "sp_sxk": "",
      "sp_type": 0,
      "spe_id": 528,
      "special_group": 0,
      "special_id": 53570,
      "spname": "建筑工程技术",
      "year": 2024,
      "zslx_name": "-",
      "data_type": "special"
    },
    {
      "average": 410,
      "doublehigh": 0,
      "dual_class_name": "",
      "first_km": 0,
      "id": "gkspecialscore20241310108",
      "info": "",
      "is_score_range": 2,
      "is_top": 2,
      "level2_name": "教育与体育大类",
      "level3_name": "语言类",
      "local_batch_name": "专科批",
      "local_province_name": "河南",
      "local_type_name": "理科",
      "max": 413,
      "min": 407,
      "min_range": "",
      "min_rank_range": "",
      "min_section": 310571,
      "name": "浙江工商职业技术学院",
      "proscore": 185,
      "remark": "",
      "school_id": 1353,
      "sg_fxk": "",
      "sg_info": "",
      "sg_name": "",
      "sg_sxk": "",
      "sg_type": 0,
      "single": "75006",
      "sp_fxk": "",
      "sp_info": "",
      "sp_name": "应用英语",
      "sp_scode": "10",
      "sp_sxk": "",
      "sp_type": 0,
      "spe_id": 1012,
      "special_group": 0,
      "special_id": 53602,
      "spname": "应用英语",
      "year": 2024,
      "zslx_name": "-",
      "data_type": "special"
    },
    {
      "average": 405,
      "doublehigh": 0,
      "dual_class_name": "",
      "first_km": 0,
      "id": "gkspecialscore20241300228",
      "info": "",
      "is_score_range": 2,
      "is_top": 2,
      "level2_name": "财经商贸大类",
      "level3_name": "经济贸易类",
      "local_batch_name": "专科批",
      "local_province_name": "河南",
      "local_type_name": "文科",
      "max": 405,
      "min": 405,
      "min_range": "",
      "min_rank_range": "",
      "min_section": 120171,
      "name": "浙江工商职业技术学院",
      "proscore": 185,
      "remark": "",
      "school_id": 1353,
      "sg_fxk": "",
      "sg_info": "",
      "sg_name": "",
      "sg_sxk": "",
      "sg_type": 0,
      "single": "75006",
      "sp_fxk": "",
      "sp_info": "",
      "sp_name": "关务与外贸服务",
      "sp_scode": "04",
      "sp_sxk": "",
      "sp_type": 0,
      "spe_id": 9089,
      "special_group": 0,
      "special_id": 1597955,
      "spname": "关务与外贸服务",
      "year": 2024,
      "zslx_name": "-",
      "data_type": "special"
    },
    {
      "average": 402,
      "doublehigh": 0,
      "dual_class_name": "",
      "first_km": 0,
      "id": "gkspecialscore20241310104",
      "info": "",
      "is_score_range": 2,
      "is_top": 2,
      "level2_name": "财经商贸大类",
      "level3_name": "财务会计类",
      "local_batch_name": "专科批",
      "local_province_name": "河南",
      "local_type_name": "理科",
      "max": 402,
      "min": 402,
      "min_range": "",
      "min_rank_range": "",
      "min_section": 319291,
      "name": "浙江工商职业技术学院",
      "proscore": 185,
      "remark": "",
      "school_id": 1353,
      "sg_fxk": "",
      "sg_info": "",
      "sg_name": "",
      "sg_sxk": "",
      "sg_type": 0,
      "single": "75006",
      "sp_fxk": "",
      "sp_info": "",
      "sp_name": "大数据与会计",
      "sp_scode": "06",
      "sp_sxk": "",
      "sp_type": 0,
      "spe_id": 9085,
      "special_group": 0,
      "special_id": 1593453,
      "spname": "大数据与会计",
      "year": 2024,
      "zslx_name": "-",
      "data_type": "special"
    },
    {
      "average": 399,
      "doublehigh": 0,
      "dual_class_name": "",
      "first_km": 0,
      "id": "gkspecialscore20241310102",
      "info": "（办学地点:慈溪校区;第一学年在慈溪校区，第二学年起在宁波本部校区）",
      "is_score_range": 2,
      "is_top": 2,
      "level2_name": "电子与信息大类",
      "level3_name": "计算机类",
      "local_batch_name": "专科批",
      "local_province_name": "河南",
      "local_type_name": "理科",
      "max": 399,
      "min": 399,
      "min_range": "",
      "min_rank_range": "",
      "min_section": 324400,
      "name": "浙江工商职业技术学院",
      "proscore": 185,
      "remark": "",
      "school_id": 1353,
      "sg_fxk": "",
      "sg_info": "",
      "sg_name": "",
      "sg_sxk": "",
      "sg_type": 0,
      "single": "75006",
      "sp_fxk": "",
      "sp_info": "",
      "sp_name": "人工智能技术应用",
      "sp_scode": "04",
      "sp_sxk": "",
      "sp_type": 0,
      "spe_id": 9060,
      "special_group": 0,
      "special_id": 1903504,
      "spname": "人工智能技术应用（办学地点:慈溪校区;第一学年在慈溪校区，第二学年起在宁波本部校区）",
      "year": 2024,
      "zslx_name": "-",
      "data_type": "special"
    },
    {
      "average": 402,
      "doublehigh": 0,
      "dual_class_name": "",
      "first_km": 0,
      "id": "gkspecialscore20241310100",
      "info": "（办学地点:宁海校区）",
      "is_score_range": 2,
      "is_top": 2,
      "level2_name": "装备制造大类",
      "level3_name": "自动化类",
      "local_batch_name": "专科批",
      "local_province_name": "河南",
      "local_type_name": "理科",
      "max": 408,
      "min": 399,
      "min_range": "",
      "min_rank_range": "",
      "min_section": 324400,
      "name": "浙江工商职业技术学院",
      "proscore": 185,
      "remark": "",
      "school_id": 1353,
      "sg_fxk": "",
      "sg_info": "",
      "sg_name": "",
      "sg_sxk": "",
      "sg_type": 0,
      "single": "75006",
      "sp_fxk": "",
      "sp_info": "",
      "sp_name": "机电一体化技术",
      "sp_scode": "02",
      "sp_sxk": "",
      "sp_type": 0,
      "spe_id": 592,
      "special_group": 0,
      "special_id": 53588,
      "spname": "机电一体化技术（办学地点:宁海校区）",
      "year": 2024,
      "zslx_name": "-",
      "data_type": "special"
    },
    {
      "average": 398,
      "doublehigh": 0,
      "dual_class_name": "",
      "first_km": 0,
      "id": "gkspecialscore20241310105",
      "info": "",
      "is_score_range": 2,
      "is_top": 2,
      "level2_name": "财经商贸大类",
      "level3_name": "电子商务类",
      "local_batch_name": "专科批",
      "local_province_name": "河南",
      "local_type_name": "理科",
      "max": 398,
      "min": 398,
      "min_range": "",
      "min_rank_range": "",
      "min_section": 326147,
      "name": "浙江工商职业技术学院",
      "proscore": 185,
      "remark": "",
      "school_id": 1353,
      "sg_fxk": "",
      "sg_info": "",
      "sg_name": "",
      "sg_sxk": "",
      "sg_type": 0,
      "single": "75006",
      "sp_fxk": "",
      "sp_info": "",
      "sp_name": "电子商务",
      "sp_scode": "07",
      "sp_sxk": "",
      "sp_type": 0,
      "spe_id": 886,
      "special_group": 0,
      "special_id": 53576,
      "spname": "电子商务",
      "year": 2024,
      "zslx_name": "-",
      "data_type": "special"
    },
    {
      "average": 398,
      "doublehigh": 0,
      "dual_class_name": "",
      "first_km": 0,
      "id": "gkspecialscore20241310099",
      "info": "",
      "is_score_range": 2,
      "is_top": 2,
      "level2_name": "土木建筑大类",
      "level3_name": "土建施工类",
      "local_batch_name": "专科批",
      "local_province_name": "河南",
      "local_type_name": "理科",
      "max": 398,
      "min": 398,
      "min_range": "",
      "min_rank_range": "",
      "min_section": 326147,
      "name": "浙江工商职业技术学院",
      "proscore": 185,
      "remark": "",
      "school_id": 1353,
      "sg_fxk": "",
      "sg_info": "",
      "sg_name": "",
      "sg_sxk": "",
      "sg_type": 0,
      "single": "75006",
      "sp_fxk": "",
      "sp_info": "",
      "sp_name": "建筑工程技术",
      "sp_scode": "01",
      "sp_sxk": "",
      "sp_type": 0,
      "spe_id": 528,
      "special_group": 0,
      "special_id": 53570,
      "spname": "建筑工程技术",
      "year": 2024,
      "zslx_name": "-",
      "data_type": "special"
    },
    {
      "average": 397,
      "doublehigh": 0,
      "dual_class_name": "",
      "first_km": 0,
      "id": "gkspecialscore20241310103",
      "info": "",
      "is_score_range": 2,
      "is_top": 2,
      "level2_name": "财经商贸大类",
      "level3_name": "金融类",
      "local_batch_name": "专科批",
      "local_province_name": "河南",
      "local_type_name": "理科",
      "max": 397,
      "min": 397,
      "min_range": "",
      "min_rank_range": "",
      "min_section": 327848,
      "name": "浙江工商职业技术学院",
      "proscore": 185,
      "remark": "",
      "school_id": 1353,
      "sg_fxk": "",
      "sg_info": "",
      "sg_name": "",
      "sg_sxk": "",
      "sg_type": 0,
      "single": "75006",
      "sp_fxk": "",
      "sp_info": "",
      "sp_name": "金融服务与管理",
      "sp_scode": "05",
      "sp_sxk": "",
      "sp_type": 0,
      "spe_id": 9180,
      "special_group": 0,
      "special_id": 1620889,
      "spname": "金融服务与管理",
      "year": 2024,
      "zslx_name": "-",
      "data_type": "special"
    },
    {
      "average": 396,
      "doublehigh": 0,
      "dual_class_name": "",
      "first_km": 0,
      "id": "gkspecialscore20241310106",
      "info": "",
      "is_score_range": 2,
      "is_top": 2,
      "level2_name": "旅游大类",
      "level3_name": "旅游类",
      "local_batch_name": "专科批",
      "local_province_name": "河南",
      "local_type_name": "理科",
      "max": 396,
      "min": 396,
      "min_range": "",
      "min_rank_range": "",
      "min_section": 329573,
      "name": "浙江工商职业技术学院",
      "proscore": 185,
      "remark": "",
      "school_id": 1353,
      "sg_fxk": "",
      "sg_info": "",
      "sg_name": "",
      "sg_sxk": "",
      "sg_type": 0,
      "single": "75006",
      "sp_fxk": "",
      "sp_info": "",
      "sp_name": "旅游管理",
      "sp_scode": "08",
      "sp_sxk": "",
      "sp_type": 0,
      "spe_id": 896,
      "special_group": 0,
      "special_id": 53573,
      "spname": "旅游管理",
      "year": 2024,
      "zslx_name": "-",
      "data_type": "special"
    },
    {
      "average": 399,
      "doublehigh": 0,
      "dual_class_name": "",
      "first_km": 0,
      "id": "gkspecialscore20241310101",
      "info": "（第一学年在宁波本部校区，第二学年起在慈溪校区）",
      "is_score_range": 2,
      "is_top": 2,
      "level2_name": "电子与信息大类",
      "level3_name": "电子信息类",
      "local_batch_name": "专科批",
      "local_province_name": "河南",
      "local_type_name": "理科",
      "max": 401,
      "min": 396,
      "min_range": "",
      "min_rank_range": "",
      "min_section": 329573,
      "name": "浙江工商职业技术学院",
      "proscore": 185,
      "remark": "",
      "school_id": 1353,
      "sg_fxk": "",
      "sg_info": "",
      "sg_name": "",
      "sg_sxk": "",
      "sg_type": 0,
      "single": "75006",
      "sp_fxk": "",
      "sp_info": "",
      "sp_name": "电子信息工程技术",
      "sp_scode": "03",
      "sp_sxk": "",
      "sp_type": 0,
      "spe_id": 764,
      "special_group": 0,
      "special_id": 2157781,
      "spname": "电子信息工程技术（第一学年在宁波本部校区，第二学年起在慈溪校区）",
      "year": 2024,
      "zslx_name": "-",
      "data_type": "special"
    },
    {
      "average": 395,
      "doublehigh": 0,
      "dual_class_name": "",
      "first_km": 0,
      "id": "gkspecialscore20241300231",
      "info": "",
      "is_score_range": 2,
      "is_top": 2,
      "level2_name": "旅游大类",
      "level3_name": "旅游类",
      "local_batch_name": "专科批",
      "local_province_name": "河南",
      "local_type_name": "文科",
      "max": 395,
      "min": 395,
      "min_range": "",
      "min_rank_range": "",
      "min_section": 130725,
      "name": "浙江工商职业技术学院",
      "proscore": 185,
      "remark": "",
      "school_id": 1353,
      "sg_fxk": "",
      "sg_info": "",
      "sg_name": "",
      "sg_sxk": "",
      "sg_type": 0,
      "single": "75006",
      "sp_fxk": "",
      "sp_info": "",
      "sp_name": "旅游管理",
      "sp_scode": "07",
      "sp_sxk": "",
      "sp_type": 0,
      "spe_id": 896,
      "special_group": 0,
      "special_id": 53573,
      "spname": "旅游管理",
      "year": 2024,
      "zslx_name": "-",
      "data_type": "special"
    },
    {
      "average": 399,
      "doublehigh": 0,
      "dual_class_name": "",
      "first_km": 0,
      "id": "gkspecialscore20241300226",
      "info": "",
      "is_score_range": 2,
      "is_top": 2,
      "level2_name": "财经商贸大类",
      "level3_name": "金融类",
      "local_batch_name": "专科批",
      "local_province_name": "河南",
      "local_type_name": "文科",
      "max": 403,
      "min": 395,
      "min_range": "",
      "min_rank_range": "",
      "min_section": 130725,
      "name": "浙江工商职业技术学院",
      "proscore": 185,
      "remark": "",
      "school_id": 1353,
      "sg_fxk": "",
      "sg_info": "",
      "sg_name": "",
      "sg_sxk": "",
      "sg_type": 0,
      "single": "75006",
      "sp_fxk": "",
      "sp_info": "",
      "sp_name": "金融服务与管理",
      "sp_scode": "02",
      "sp_sxk": "",
      "sp_type": 0,
      "spe_id": 9180,
      "special_group": 0,
      "special_id": 1620889,
      "spname": "金融服务与管理",
      "year": 2024,
      "zslx_name": "-",
      "data_type": "special"
    },
    {
      "average": 392,
      "doublehigh": 0,
      "dual_class_name": "",
      "first_km": 0,
      "id": "gkspecialscore20241310107",
      "info": "",
      "is_score_range": 2,
      "is_top": 2,
      "level2_name": "旅游大类",
      "level3_name": "旅游类",
      "local_batch_name": "专科批",
      "local_province_name": "河南",
      "local_type_name": "理科",
      "max": 392,
      "min": 392,
      "min_range": "",
      "min_rank_range": "",
      "min_section": 336443,
      "name": "浙江工商职业技术学院",
      "proscore": 185,
      "remark": "",
      "school_id": 1353,
      "sg_fxk": "",
      "sg_info": "",
      "sg_name": "",
      "sg_sxk": "",
      "sg_type": 0,
      "single": "75006",
      "sp_fxk": "",
      "sp_info": "",
      "sp_name": "研学旅行管理与服务",
      "sp_scode": "09",
      "sp_sxk": "",
      "sp_type": 0,
      "spe_id": 8557,
      "special_group": 0,
      "special_id": 1868598,
      "spname": "研学旅行管理与服务",
      "year": 2024,
      "zslx_name": "-",
      "data_type": "special"
    },
    {
      "average": 399,
      "doublehigh": 0,
      "dual_class_name": "",
      "first_km": 0,
      "id": "gkspecialscore20241300232",
      "info": "",
      "is_score_range": 2,
      "is_top": 2,
      "level2_name": "旅游大类",
      "level3_name": "旅游类",
      "local_batch_name": "专科批",
      "local_province_name": "河南",
      "local_type_name": "文科",
      "max": 407,
      "min": 390,
      "min_range": "",
      "min_rank_range": "",
      "min_section": 136143,
      "name": "浙江工商职业技术学院",
      "proscore": 185,
      "remark": "",
      "school_id": 1353,
      "sg_fxk": "",
      "sg_info": "",
      "sg_name": "",
      "sg_sxk": "",
      "sg_type": 0,
      "single": "75006",
      "sp_fxk": "",
      "sp_info": "",
      "sp_name": "研学旅行管理与服务",
      "sp_scode": "08",
      "sp_sxk": "",
      "sp_type": 0,
      "spe_id": 8557,
      "special_group": 0,
      "special_id": 1868598,
      "spname": "研学旅行管理与服务",
      "year": 2024,
      "zslx_name": "-",
      "data_type": "special"
    }
  ]
}