{
  "school_id": 832,
  "name": "中国石油大学（北京）",
  "level": "本科",
  "is_985": false,
  "is_211": true,
  "dual_class": "双一流",
  "city": "北京市",
  "province": "北京",
  "type": "理工类",
  "nature": "公办",
  "province_scores": [
    {
      "admissions": "2",
      "answerurl": "https://answer.eol.cn/fillmess/index?id=3293&source=zsgk_app",
      "average": "-",
      "avg_section": "-",
      "city_name": "北京市",
      "county_name": "昌平区",
      "diff": 59,
      "doublehigh": "0",
      "dual_class": 38000,
      "dual_class_name": "双一流",
      "f211": 1,
      "f985": 2,
      "filing": 606,
      "first_km": 0,
      "level_name": "本科",
      "local_batch_id": "7",
      "local_batch_name": "本科一批",
      "local_province_name": "河南",
      "local_type_name": "文科",
      "major_score": "-",
      "max": "-",
      "min": 606,
      "min_section": 3681,
      "name": "中国石油大学（北京）",
      "nature_name": "公办",
      "num": "-",
      "proscore": 547,
      "province_id": 11,
      "province_name": "北京",
      "school_id": 832,
      "sg_fxk": 0,
      "sg_info": "",
      "sg_name": "",
      "sg_sxk": "",
      "sg_type": 0,
      "special_group": "0",
      "type_name": "理工类",
      "xclevel_name": "",
      "year": 2023,
      "zslx_name": "普通类",
      "data_type": "province"
    },
    {
      "admissions": "2",
      "answerurl": "https://answer.eol.cn/fillmess/index?id=3293&source=zsgk_app",
      "average": "-",
      "avg_section": "-",
      "city_name": "北京市",
      "county_name": "昌平区",
      "diff": 87,
      "doublehigh": "0",
      "dual_class": 38000,
      "dual_class_name": "双一流",
      "f211": 1,
      "f985": 2,
      "filing": 601,
      "first_km": 0,
      "level_name": "本科",
      "local_batch_id": "7",
      "local_batch_name": "本科一批",
      "local_province_name": "河南",
      "local_type_name": "理科",
      "major_score": "-",
      "max": "-",
      "min": 601,
      "min_section": 21021,
      "name": "中国石油大学（北京）",
      "nature_name": "公办",
      "num": "-",
      "proscore": 514,
      "province_id": 11,
      "province_name": "北京",
      "school_id": 832,
      "sg_fxk": 0,
      "sg_info": "",
      "sg_name": "",
      "sg_sxk": "",
      "sg_type": 0,
      "special_group": "0",
      "type_name": "理工类",
      "xclevel_name": "",
      "year": 2023,
      "zslx_name": "普通类",
      "data_type": "province"
    },
    {
      "admissions": "2",
      "answerurl": "https://answer.eol.cn/fillmess/index?id=3293&source=zsgk_app",
      "average": "-",
      "avg_section": "-",
      "city_name": "北京市",
      "county_name": "昌平区",
      "diff": 93,
      "doublehigh": "0",
      "dual_class": 38000,
      "dual_class_name": "双一流",
      "f211": 1,
      "f985": 2,
      "filing": 0,
      "first_km": 0,
      "level_name": "本科",
      "local_batch_id": "7",
      "local_batch_name": "本科一批",
      "local_province_name": "河南",
      "local_type_name": "理科",
      "major_score": "-",
      "max": "-",
      "min": 604,
      "min_section": 21039,
      "name": "中国石油大学（北京）",
      "nature_name": "公办",
      "num": "-",
      "proscore": 511,
      "province_id": 11,
      "province_name": "北京",
      "school_id": 832,
      "sg_fxk": 0,
      "sg_info": "",
      "sg_name": "",
      "sg_sxk": "",
      "sg_type": 0,
      "special_group": "0",
      "type_name": "理工类",
      "xclevel_name": "",
      "year": 2024,
      "zslx_name": "普通类",
      "data_type": "province"
    },
    {
      "admissions": "2",
      "answerurl": "https://answer.eol.cn/fillmess/index?id=3293&source=zsgk_app",
      "average": "-",
      "avg_section": "-",
      "city_name": "北京市",
      "county_name": "昌平区",
      "diff": 60,
      "doublehigh": "0",
      "dual_class": 38000,
      "dual_class_name": "双一流",
      "f211": 1,
      "f985": 2,
      "filing": 0,
      "first_km": 0,
      "level_name": "本科",
      "local_batch_id": "7",
      "local_batch_name": "本科一批",
      "local_province_name": "河南",
      "local_type_name": "文科",
      "major_score": "-",
      "max": "-",
      "min": 581,
      "min_section": 4526,
      "name": "中国石油大学（北京）",
      "nature_name": "公办",
      "num": "-",
      "proscore": 521,
      "province_id": 11,
      "province_name": "北京",
      "school_id": 832,
      "sg_fxk": 0,
      "sg_info": "",
      "sg_name": "",
      "sg_sxk": "",
      "sg_type": 0,
      "special_group": "0",
      "type_name": "理工类",
      "xclevel_name": "",
      "year": 2024,
      "zslx_name": "普通类",
      "data_type": "province"
    },
    {
      "admissions": "2",
      "answerurl": "https://answer.eol.cn/fillmess/index?id=3293&source=zsgk_app",
      "average": "-",
      "avg_section": "-",
      "city_name": "北京市",
      "county_name": "昌平区",
      "diff": 205,
      "doublehigh": "0",
      "dual_class": 38000,
      "dual_class_name": "双一流",
      "f211": 1,
      "f985": 2,
      "filing": 0,
      "first_km": 70000,
      "level_name": "本科",
      "local_batch_id": "14",
      "local_batch_name": "本科批",
      "local_province_name": "河南",
      "local_type_name": "物理类",
      "major_score": "-",
      "max": 658,
      "min": 632,
      "min_section": 17632,
      "name": "中国石油大学（北京）",
      "nature_name": "公办",
      "num": "-",
      "proscore": 427,
      "province_id": 11,
      "province_name": "北京",
      "school_id": 832,
      "sg_fxk": 70000,
      "sg_info": "首选物理，再选化学",
      "sg_name": "（101）",
      "sg_sxk": "70001",
      "sg_type": 80003,
      "special_group": "503078",
      "type_name": "理工类",
      "xclevel_name": "",
      "year": 2025,
      "zslx_name": "普通类",
      "data_type": "province"
    },
    {
      "admissions": "2",
      "answerurl": "https://answer.eol.cn/fillmess/index?id=3293&source=zsgk_app",
      "average": "-",
      "avg_section": "-",
      "city_name": "北京市",
      "county_name": "昌平区",
      "diff": 198,
      "doublehigh": "0",
      "dual_class": 38000,
      "dual_class_name": "双一流",
      "f211": 1,
      "f985": 2,
      "filing": 0,
      "first_km": 70000,
      "level_name": "本科",
      "local_batch_id": "14",
      "local_batch_name": "本科批",
      "local_province_name": "河南",
      "local_type_name": "物理类",
      "major_score": "-",
      "max": 636,
      "min": 625,
      "min_section": 22450,
      "name": "中国石油大学（北京）",
      "nature_name": "公办",
      "num": "-",
      "proscore": 427,
      "province_id": 11,
      "province_name": "北京",
      "school_id": 832,
      "sg_fxk": 70000,
      "sg_info": "首选物理，再选不限",
      "sg_name": "（102）",
      "sg_sxk": "70008",
      "sg_type": 80001,
      "special_group": "503091",
      "type_name": "理工类",
      "xclevel_name": "",
      "year": 2025,
      "zslx_name": "普通类",
      "data_type": "province"
    },
    {
      "admissions": "2",
      "answerurl": "https://answer.eol.cn/fillmess/index?id=3293&source=zsgk_app",
      "average": "-",
      "avg_section": "-",
      "city_name": "北京市",
      "county_name": "昌平区",
      "diff": 144,
      "doublehigh": "0",
      "dual_class": 38000,
      "dual_class_name": "双一流",
      "f211": 1,
      "f985": 2,
      "filing": 0,
      "first_km": 70004,
      "level_name": "本科",
      "local_batch_id": "14",
      "local_batch_name": "本科批",
      "local_province_name": "河南",
      "local_type_name": "历史类",
      "major_score": "-",
      "max": 619,
      "min": 615,
      "min_section": 3337,
      "name": "中国石油大学（北京）",
      "nature_name": "公办",
      "num": "-",
      "proscore": 471,
      "province_id": 11,
      "province_name": "北京",
      "school_id": 832,
      "sg_fxk": 70004,
      "sg_info": "首选历史，再选思想政治",
      "sg_name": "（103）",
      "sg_sxk": "70003",
      "sg_type": 80003,
      "special_group": "503098",
      "type_name": "理工类",
      "xclevel_name": "",
      "year": 2025,
      "zslx_name": "普通类",
      "data_type": "province"
    },
    {
      "admissions": "2",
      "answerurl": "https://answer.eol.cn/fillmess/index?id=3293&source=zsgk_app",
      "average": "-",
      "avg_section": "-",
      "city_name": "北京市",
      "county_name": "昌平区",
      "diff": 142,
      "doublehigh": "0",
      "dual_class": 38000,
      "dual_class_name": "双一流",
      "f211": 1,
      "f985": 2,
      "filing": 0,
      "first_km": 70004,
      "level_name": "本科",
      "local_batch_id": "14",
      "local_batch_name": "本科批",
      "local_province_name": "河南",
      "local_type_name": "历史类",
      "major_score": "-",
      "max": 616,
      "min": 613,
      "min_section": 3645,
      "name": "中国石油大学（北京）",
      "nature_name": "公办",
      "num": "-",
      "proscore": 471,
      "province_id": 11,
      "province_name": "北京",
      "school_id": 832,
      "sg_fxk": 70004,
      "sg_info": "首选历史，再选不限",
      "sg_name": "（104）",
      "sg_sxk": "70008",
      "sg_type": 80001,
      "special_group": "503099",
      "type_name": "理工类",
      "xclevel_name": "",
      "year": 2025,
      "zslx_name": "普通类",
      "data_type": "province"
    },
    {
      "admissions": "2",
      "answerurl": "https://answer.eol.cn/fillmess/index?id=3293&source=zsgk_app",
      "average": "-",
      "avg_section": "-",
      "city_name": "北京市",
      "county_name": "昌平区",
      "diff": 181,
      "doublehigh": "0",
      "dual_class": 38000,
      "dual_class_name": "双一流",
      "f211": 1,
      "f985": 2,
      "filing": 0,
      "first_km": 70000,
      "level_name": "本科",
      "local_batch_id": "14",
      "local_batch_name": "本科批",
      "local_province_name": "河南",
      "local_type_name": "物理类",
      "major_score": "-",
      "max": 622,
      "min": 608,
      "min_section": 37473,
      "name": "中国石油大学（北京）",
      "nature_name": "公办",
      "num": "-",
      "proscore": 427,
      "province_id": 11,
      "province_name": "北京",
      "school_id": 832,
      "sg_fxk": 70000,
      "sg_info": "首选物理，再选化学",
      "sg_name": "（301）",
      "sg_sxk": "70001",
      "sg_type": 80003,
      "special_group": "503110",
      "type_name": "理工类",
      "xclevel_name": "",
      "year": 2025,
      "zslx_name": "国家专项",
      "data_type": "province"
    }
  ],
  "special_scores": [
    {
      "average": 619,
      "doublehigh": 0,
      "dual_class_name": "",
      "first_km": 0,
      "id": "gkspecialscore2023789556",
      "info": "",
      "is_score_range": 2,
      "is_top": 2,
      "level2_name": "工学",
      "level3_name": "计算机类",
      "local_batch_name": "本科一批",
      "local_province_name": "河南",
      "local_type_name": "理科",
      "max": 624,
      "min": 617,
      "min_range": "",
      "min_rank_range": "",
      "min_section": 12626,
      "name": "中国石油大学（北京）",
      "proscore": 514,
      "remark": "",
      "school_id": 832,
      "sg_fxk": "",
      "sg_info": "",
      "sg_name": "",
      "sg_sxk": "",
      "sg_type": 0,
      "single": "",
      "sp_fxk": "",
      "sp_info": "",
      "sp_name": "计算机科学与技术",
      "sp_scode": "14",
      "sp_sxk": "",
      "sp_type": 0,
      "spe_id": 172,
      "special_group": 0,
      "special_id": 37282,
      "spname": "计算机科学与技术",
      "year": 2023,
      "zslx_name": "-",
      "data_type": "special"
    },
    {
      "average": 614,
      "doublehigh": 0,
      "dual_class_name": "",
      "first_km": 0,
      "id": "gkspecialscore2023789555",
      "info": "",
      "is_score_range": 2,
      "is_top": 2,
      "level2_name": "工学",
      "level3_name": "自动化类",
      "local_batch_name": "本科一批",
      "local_province_name": "河南",
      "local_type_name": "理科",
      "max": 615,
      "min": 614,
      "min_range": "",
      "min_rank_range": "",
      "min_section": 13937,
      "name": "中国石油大学（北京）",
      "proscore": 514,
      "remark": "",
      "school_id": 832,
      "sg_fxk": "",
      "sg_info": "",
      "sg_name": "",
      "sg_sxk": "",
      "sg_type": 0,
      "single": "",
      "sp_fxk": "",
      "sp_info": "",
      "sp_name": "自动化",
      "sp_scode": "13",
      "sp_sxk": "",
      "sp_type": 0,
      "spe_id": 171,
      "special_group": 0,
      "special_id": 37280,
      "spname": "自动化",
      "year": 2023,
      "zslx_name": "-",
      "data_type": "special"
    },
    {
      "average": 615,
      "doublehigh": 0,
      "dual_class_name": "",
      "first_km": 0,
      "id": "gkspecialscore2023789553",
      "info": "",
      "is_score_range": 2,
      "is_top": 2,
      "level2_name": "工学",
      "level3_name": "电子信息类",
      "local_batch_name": "本科一批",
      "local_province_name": "河南",
      "local_type_name": "理科",
      "max": 616,
      "min": 614,
      "min_range": "",
      "min_rank_range": "",
      "min_section": 13937,
      "name": "中国石油大学（北京）",
      "proscore": 514,
      "remark": "",
      "school_id": 832,
      "sg_fxk": "",
      "sg_info": "",
      "sg_name": "",
      "sg_sxk": "",
      "sg_type": 0,
      "single": "",
      "sp_fxk": "",
      "sp_info": "",
      "sp_name": "电子信息工程",
      "sp_scode": "11",
      "sp_sxk": "",
      "sp_type": 0,
      "spe_id": 165,
      "special_group": 0,
      "special_id": 37281,
      "spname": "电子信息工程",
      "year": 2023,
      "zslx_name": "-",
      "data_type": "special"
    },
    {
      "average": 612,
      "doublehigh": 0,
      "dual_class_name": "",
      "first_km": 0,
      "id": "gkspecialscore2023789554",
      "info": "",
      "is_score_range": 2,
      "is_top": 2,
      "level2_name": "工学",
      "level3_name": "电子信息类",
      "local_batch_name": "本科一批",
      "local_province_name": "河南",
      "local_type_name": "理科",
      "max": 613,
      "min": 612,
      "min_range": "",
      "min_rank_range": "",
      "min_section": 14902,
      "name": "中国石油大学（北京）",
      "proscore": 514,
      "remark": "",
      "school_id": 832,
      "sg_fxk": "",
      "sg_info": "",
      "sg_name": "",
      "sg_sxk": "",
      "sg_type": 0,
      "single": "",
      "sp_fxk": "",
      "sp_info": "",
      "sp_name": "人工智能",
      "sp_scode": "12",
      "sp_sxk": "",
      "sp_type": 0,
      "spe_id": 8387,
      "special_group": 0,
      "special_id": 1129617,
      "spname": "人工智能",
      "year": 2023,
      "zslx_name": "-",
      "data_type": "special"
    },
    {
      "average": 613,
      "doublehigh": 0,
      "dual_class_name": "",
      "first_km": 0,
      "id": "gkspecialscore2023789551",
      "info": "",
      "is_score_range": 2,
      "is_top": 2,
      "level2_name": "工学",
      "level3_name": "能源动力类",
      "local_batch_name": "本科一批",
      "local_province_name": "河南",
      "local_type_name": "理科",
      "max": 616,
      "min": 611,
      "min_range": "",
      "min_rank_range": "",
      "min_section": 15415,
      "name": "中国石油大学（北京）",
      "proscore": 514,
      "remark": "",
      "school_id": 832,
      "sg_fxk": "",
      "sg_info": "",
      "sg_name": "",
      "sg_sxk": "",
      "sg_type": 0,
      "single": "",
      "sp_fxk": "",
      "sp_info": "",
      "sp_name": "新能源科学与工程",
      "sp_scode": "09",
      "sp_sxk": "",
      "sp_type": 0,
      "spe_id": 1152,
      "special_group": 0,
      "special_id": 174517,
      "spname": "新能源科学与工程",
      "year": 2023,
      "zslx_name": "-",
      "data_type": "special"
    },
    {
      "average": 613,
      "doublehigh": 0,
      "dual_class_name": "",
      "first_km": 0,
      "id": "gkspecialscore2023789559",
      "info": "",
      "is_score_range": 2,
      "is_top": 2,
      "level2_name": "工学",
      "level3_name": "矿业类",
      "local_batch_name": "本科一批",
      "local_province_name": "河南",
      "local_type_name": "理科",
      "max": 626,
      "min": 610,
      "min_range": "",
      "min_rank_range": "",
      "min_section": 15925,
      "name": "中国石油大学（北京）",
      "proscore": 514,
      "remark": "",
      "school_id": 832,
      "sg_fxk": "",
      "sg_info": "",
      "sg_name": "",
      "sg_sxk": "",
      "sg_type": 0,
      "single": "",
      "sp_fxk": "",
      "sp_info": "",
      "sp_name": "石油工程",
      "sp_scode": "17",
      "sp_sxk": "",
      "sp_type": 0,
      "spe_id": 193,
      "special_group": 0,
      "special_id": 37264,
      "spname": "石油工程",
      "year": 2023,
      "zslx_name": "-",
      "data_type": "special"
    },
    {
      "average": 610,
      "doublehigh": 0,
      "dual_class_name": "",
      "first_km": 0,
      "id": "gkspecialscore2023789547",
      "info": "（包含专业:机器人工程，机械设计制造及其自动化）",
      "is_score_range": 2,
      "is_top": 2,
      "level2_name": "工学",
      "level3_name": "机械类",
      "local_batch_name": "本科一批",
      "local_province_name": "河南",
      "local_type_name": "理科",
      "max": 613,
      "min": 609,
      "min_range": "",
      "min_rank_range": "",
      "min_section": 16466,
      "name": "中国石油大学（北京）",
      "proscore": 514,
      "remark": "",
      "school_id": 832,
      "sg_fxk": "",
      "sg_info": "",
      "sg_name": "",
      "sg_sxk": "",
      "sg_type": 0,
      "single": "",
      "sp_fxk": "",
      "sp_info": "",
      "sp_name": "机械类",
      "sp_scode": "05",
      "sp_sxk": "",
      "sp_type": 0,
      "spe_id": 1345,
      "special_group": 0,
      "special_id": 109430,
      "spname": "机械类（包含专业:机器人工程，机械设计制造及其自动化）",
      "year": 2023,
      "zslx_name": "-",
      "data_type": "special"
    },
    {
      "average": 610,
      "doublehigh": 0,
      "dual_class_name": "",
      "first_km": 0,
      "id": "gkspecialscore2023789544",
      "info": "（包含专业:数学与应用数学，统计学）",
      "is_score_range": 2,
      "is_top": 2,
      "level2_name": "理学",
      "level3_name": "数学类",
      "local_batch_name": "本科一批",
      "local_province_name": "河南",
      "local_type_name": "理科",
      "max": 612,
      "min": 609,
      "min_range": "",
      "min_rank_range": "",
      "min_section": 16466,
      "name": "中国石油大学（北京）",
      "proscore": 514,
      "remark": "",
      "school_id": 832,
      "sg_fxk": "",
      "sg_info": "",
      "sg_name": "",
      "sg_sxk": "",
      "sg_type": 0,
      "single": "",
      "sp_fxk": "",
      "sp_info": "",
      "sp_name": "数学类",
      "sp_scode": "02",
      "sp_sxk": "",
      "sp_type": 0,
      "spe_id": 1332,
      "special_group": 0,
      "special_id": 727986,
      "spname": "数学类（包含专业:数学与应用数学，统计学）",
      "year": 2023,
      "zslx_name": "-",
      "data_type": "special"
    },
    {
      "average": 609,
      "doublehigh": 0,
      "dual_class_name": "",
      "first_km": 0,
      "id": "gkspecialscore2023786080",
      "info": "",
      "is_score_range": 2,
      "is_top": 2,
      "level2_name": "法学",
      "level3_name": "马克思主义理论类",
      "local_batch_name": "本科一批",
      "local_province_name": "河南",
      "local_type_name": "文科",
      "max": 609,
      "min": 609,
      "min_range": "",
      "min_rank_range": "",
      "min_section": 3260,
      "name": "中国石油大学（北京）",
      "proscore": 547,
      "remark": "",
      "school_id": 832,
      "sg_fxk": "",
      "sg_info": "",
      "sg_name": "",
      "sg_sxk": "",
      "sg_type": 0,
      "single": "",
      "sp_fxk": "",
      "sp_info": "",
      "sp_name": "思想政治教育",
      "sp_scode": "01",
      "sp_sxk": "",
      "sp_type": 0,
      "spe_id": 23,
      "special_group": 0,
      "special_id": 1129615,
      "spname": "思想政治教育",
      "year": 2023,
      "zslx_name": "-",
      "data_type": "special"
    },
    {
      "average": 608,
      "doublehigh": 0,
      "dual_class_name": "",
      "first_km": 0,
      "id": "gkspecialscore2023789564",
      "info": "（包含专业:环境工程，环境科学）",
      "is_score_range": 2,
      "is_top": 2,
      "level2_name": "工学",
      "level3_name": "环境科学与工程类",
      "local_batch_name": "本科一批",
      "local_province_name": "河南",
      "local_type_name": "理科",
      "max": 609,
      "min": 608,
      "min_range": "",
      "min_rank_range": "",
      "min_section": 17028,
      "name": "中国石油大学（北京）",
      "proscore": 514,
      "remark": "",
      "school_id": 832,
      "sg_fxk": "",
      "sg_info": "",
      "sg_name": "",
      "sg_sxk": "",
      "sg_type": 0,
      "single": "",
      "sp_fxk": "",
      "sp_info": "",
      "sp_name": "环境科学与工程类",
      "sp_scode": "22",
      "sp_sxk": "",
      "sp_type": 0,
      "spe_id": 1368,
      "special_group": 0,
      "special_id": 204103,
      "spname": "环境科学与工程类（包含专业:环境工程，环境科学）",
      "year": 2023,
      "zslx_name": "-",
      "data_type": "special"
    },
    {
      "average": 609,
      "doublehigh": 0,
      "dual_class_name": "",
      "first_km": 0,
      "id": "gkspecialscore2023789550",
      "info": "",
      "is_score_range": 2,
      "is_top": 2,
      "level2_name": "工学",
      "level3_name": "能源动力类",
      "local_batch_name": "本科一批",
      "local_province_name": "河南",
      "local_type_name": "理科",
      "max": 612,
      "min": 608,
      "min_range": "",
      "min_rank_range": "",
      "min_section": 17028,
      "name": "中国石油大学（北京）",
      "proscore": 514,
      "remark": "",
      "school_id": 832,
      "sg_fxk": "",
      "sg_info": "",
      "sg_name": "",
      "sg_sxk": "",
      "sg_type": 0,
      "single": "",
      "sp_fxk": "",
      "sp_info": "",
      "sp_name": "能源与动力工程",
      "sp_scode": "08",
      "sp_sxk": "",
      "sp_type": 0,
      "spe_id": 163,
      "special_group": 0,
      "special_id": 37303,
      "spname": "能源与动力工程",
      "year": 2023,
      "zslx_name": "-",
      "data_type": "special"
    },
    {
      "average": 607,
      "doublehigh": 0,
      "dual_class_name": "",
      "first_km": 0,
      "id": "gkspecialscore2023789567",
      "info": "（包含专业:会计学，财务管理，市场营销）",
      "is_score_range": 2,
      "is_top": 2,
      "level2_name": "管理学",
      "level3_name": "工商管理类",
      "local_batch_name": "本科一批",
      "local_province_name": "河南",
      "local_type_name": "理科",
      "max": 608,
      "min": 606,
      "min_range": "",
      "min_rank_range": "",
      "min_section": 18105,
      "name": "中国石油大学（北京）",
      "proscore": 514,
      "remark": "",
      "school_id": 832,
      "sg_fxk": "",
      "sg_info": "",
      "sg_name": "",
      "sg_sxk": "",
      "sg_type": 0,
      "single": "",
      "sp_fxk": "",
      "sp_info": "",
      "sp_name": "工商管理类",
      "sp_scode": "25",
      "sp_sxk": "",
      "sp_type": 0,
      "spe_id": 1394,
      "special_group": 0,
      "special_id": 109418,
      "spname": "工商管理类（包含专业:会计学，财务管理，市场营销）",
      "year": 2023,
      "zslx_name": "-",
      "data_type": "special"
    },
    {
      "average": 607,
      "doublehigh": 0,
      "dual_class_name": "",
      "first_km": 0,
      "id": "gkspecialscore2023789563",
      "info": "",
      "is_score_range": 2,
      "is_top": 2,
      "level2_name": "工学",
      "level3_name": "矿业类",
      "local_batch_name": "本科一批",
      "local_province_name": "河南",
      "local_type_name": "理科",
      "max": 608,
      "min": 606,
      "min_range": "",
      "min_rank_range": "",
      "min_section": 18105,
      "name": "中国石油大学（北京）",
      "proscore": 514,
      "remark": "",
      "school_id": 832,
      "sg_fxk": "",
      "sg_info": "",
      "sg_name": "",
      "sg_sxk": "",
      "sg_type": 0,
      "single": "",
      "sp_fxk": "",
      "sp_info": "",
      "sp_name": "碳储科学与工程",
      "sp_scode": "21",
      "sp_sxk": "",
      "sp_type": 0,
      "spe_id": 9336,
      "special_group": 0,
      "special_id": 1801709,
      "spname": "碳储科学与工程",
      "year": 2023,
      "zslx_name": "-",
      "data_type": "special"
    },
    {
      "average": 607,
      "doublehigh": 0,
      "dual_class_name": "",
      "first_km": 0,
      "id": "gkspecialscore2023789552",
      "info": "",
      "is_score_range": 2,
      "is_top": 2,
      "level2_name": "工学",
      "level3_name": "能源动力类",
      "local_batch_name": "本科一批",
      "local_province_name": "河南",
      "local_type_name": "理科",
      "max": 609,
      "min": 606,
      "min_range": "",
      "min_rank_range": "",
      "min_section": 18105,
      "name": "中国石油大学（北京）",
      "proscore": 514,
      "remark": "",
      "school_id": 832,
      "sg_fxk": "",
      "sg_info": "",
      "sg_name": "",
      "sg_sxk": "",
      "sg_type": 0,
      "single": "",
      "sp_fxk": "",
      "sp_info": "",
      "sp_name": "储能科学与工程",
      "sp_scode": "10",
      "sp_sxk": "",
      "sp_type": 0,
      "spe_id": 8689,
      "special_group": 0,
      "special_id": 1500080,
      "spname": "储能科学与工程",
      "year": 2023,
      "zslx_name": "-",
      "data_type": "special"
    },
    {
      "average": 606,
      "doublehigh": 0,
      "dual_class_name": "",
      "first_km": 0,
      "id": "gkspecialscore2023789545",
      "info": "",
      "is_score_range": 2,
      "is_top": 2,
      "level2_name": "理学",
      "level3_name": "化学类",
      "local_batch_name": "本科一批",
      "local_province_name": "河南",
      "local_type_name": "理科",
      "max": 606,
      "min": 606,
      "min_range": "",
      "min_rank_range": "",
      "min_section": 18105,
      "name": "中国石油大学（北京）",
      "proscore": 514,
      "remark": "",
      "school_id": 832,
      "sg_fxk": "",
      "sg_info": "",
      "sg_name": "",
      "sg_sxk": "",
      "sg_type": 0,
      "single": "",
      "sp_fxk": "",
      "sp_info": "",
      "sp_name": "应用化学",
      "sp_scode": "03",
      "sp_sxk": "",
      "sp_type": 0,
      "spe_id": 122,
      "special_group": 0,
      "special_id": 37273,
      "spname": "应用化学",
      "year": 2023,
      "zslx_name": "-",
      "data_type": "special"
    },
    {
      "average": 607,
      "doublehigh": 0,
      "dual_class_name": "",
      "first_km": 0,
      "id": "gkspecialscore2023786081",
      "info": "（只招英语语种考生）",
      "is_score_range": 2,
      "is_top": 2,
      "level2_name": "文学",
      "level3_name": "外国语言文学类",
      "local_batch_name": "本科一批",
      "local_province_name": "河南",
      "local_type_name": "文科",
      "max": 609,
      "min": 606,
      "min_range": "",
      "min_rank_range": "",
      "min_section": 3681,
      "name": "中国石油大学（北京）",
      "proscore": 547,
      "remark": "",
      "school_id": 832,
      "sg_fxk": "",
      "sg_info": "",
      "sg_name": "",
      "sg_sxk": "",
      "sg_type": 0,
      "single": "",
      "sp_fxk": "",
      "sp_info": "",
      "sp_name": "英语",
      "sp_scode": "02",
      "sp_sxk": "",
      "sp_type": 0,
      "spe_id": 45,
      "special_group": 0,
      "special_id": 37290,
      "spname": "英语（只招英语语种考生）",
      "year": 2023,
      "zslx_name": "-",
      "data_type": "special"
    },
    {
      "average": 604,
      "doublehigh": 0,
      "dual_class_name": "",
      "first_km": 0,
      "id": "gkspecialscore2023789565",
      "info": "",
      "is_score_range": 2,
      "is_top": 2,
      "level2_name": "工学",
      "level3_name": "安全科学与工程类",
      "local_batch_name": "本科一批",
      "local_province_name": "河南",
      "local_type_name": "理科",
      "max": 606,
      "min": 604,
      "min_range": "",
      "min_rank_range": "",
      "min_section": 19248,
      "name": "中国石油大学（北京）",
      "proscore": 514,
      "remark": "",
      "school_id": 832,
      "sg_fxk": "",
      "sg_info": "",
      "sg_name": "",
      "sg_sxk": "",
      "sg_type": 0,
      "single": "",
      "sp_fxk": "",
      "sp_info": "",
      "sp_name": "安全工程",
      "sp_scode": "23",
      "sp_sxk": "",
      "sp_type": 0,
      "spe_id": 244,
      "special_group": 0,
      "special_id": 37307,
      "spname": "安全工程",
      "year": 2023,
      "zslx_name": "-",
      "data_type": "special"
    },
    {
      "average": 606,
      "doublehigh": 0,
      "dual_class_name": "",
      "first_km": 0,
      "id": "gkspecialscore2023789561",
      "info": "",
      "is_score_range": 2,
      "is_top": 2,
      "level2_name": "工学",
      "level3_name": "矿业类",
      "local_batch_name": "本科一批",
      "local_province_name": "河南",
      "local_type_name": "理科",
      "max": 611,
      "min": 604,
      "min_range": "",
      "min_rank_range": "",
      "min_section": 19248,
      "name": "中国石油大学（北京）",
      "proscore": 514,
      "remark": "",
      "school_id": 832,
      "sg_fxk": "",
      "sg_info": "",
      "sg_name": "",
      "sg_sxk": "",
      "sg_type": 0,
      "single": "",
      "sp_fxk": "",
      "sp_info": "",
      "sp_name": "油气储运工程",
      "sp_scode": "19",
      "sp_sxk": "",
      "sp_type": 0,
      "spe_id": 195,
      "special_group": 0,
      "special_id": 37276,
      "spname": "油气储运工程",
      "year": 2023,
      "zslx_name": "-",
      "data_type": "special"
    },
    {
      "average": 605,
      "doublehigh": 0,
      "dual_class_name": "",
      "first_km": 0,
      "id": "gkspecialscore2023789558",
      "info": "（包含专业:资源勘查工程，地质学）",
      "is_score_range": 2,
      "is_top": 2,
      "level2_name": "工学",
      "level3_name": "地质类",
      "local_batch_name": "本科一批",
      "local_province_name": "河南",
      "local_type_name": "理科",
      "max": 606,
      "min": 604,
      "min_range": "",
      "min_rank_range": "",
      "min_section": 19248,
      "name": "中国石油大学（北京）",
      "proscore": 514,
      "remark": "",
      "school_id": 832,
      "sg_fxk": "",
      "sg_info": "",
      "sg_name": "",
      "sg_sxk": "",
      "sg_type": 0,
      "single": "",
      "sp_fxk": "",
      "sp_info": "",
      "sp_name": "地质类",
      "sp_scode": "16",
      "sp_sxk": "",
      "sp_type": 0,
      "spe_id": 1357,
      "special_group": 0,
      "special_id": 1230475,
      "spname": "地质类（包含专业:资源勘查工程，地质学）",
      "year": 2023,
      "zslx_name": "-",
      "data_type": "special"
    },
    {
      "average": 603,
      "doublehigh": 0,
      "dual_class_name": "",
      "first_km": 0,
      "id": "gkspecialscore2023789566",
      "info": "",
      "is_score_range": 2,
      "is_top": 2,
      "level2_name": "管理学",
      "level3_name": "管理科学与工程类",
      "local_batch_name": "本科一批",
      "local_province_name": "河南",
      "local_type_name": "理科",
      "max": 605,
      "min": 603,
      "min_range": "",
      "min_rank_range": "",
      "min_section": 19849,
      "name": "中国石油大学（北京）",
      "proscore": 514,
      "remark": "",
      "school_id": 832,
      "sg_fxk": "",
      "sg_info": "",
      "sg_name": "",
      "sg_sxk": "",
      "sg_type": 0,
      "single": "",
      "sp_fxk": "",
      "sp_info": "",
      "sp_name": "信息管理与信息系统",
      "sp_scode": "24",
      "sp_sxk": "",
      "sp_type": 0,
      "spe_id": 293,
      "special_group": 0,
      "special_id": 37285,
      "spname": "信息管理与信息系统",
      "year": 2023,
      "zslx_name": "-",
      "data_type": "special"
    },
    {
      "average": 603,
      "doublehigh": 0,
      "dual_class_name": "",
      "first_km": 0,
      "id": "gkspecialscore2023789562",
      "info": "",
      "is_score_range": 2,
      "is_top": 2,
      "level2_name": "工学",
      "level3_name": "矿业类",
      "local_batch_name": "本科一批",
      "local_province_name": "河南",
      "local_type_name": "理科",
      "max": 604,
      "min": 603,
      "min_range": "",
      "min_rank_range": "",
      "min_section": 19849,
      "name": "中国石油大学（北京）",
      "proscore": 514,
      "remark": "",
      "school_id": 832,
      "sg_fxk": "",
      "sg_info": "",
      "sg_name": "",
      "sg_sxk": "",
      "sg_type": 0,
      "single": "",
      "sp_fxk": "",
      "sp_info": "",
      "sp_name": "海洋油气工程",
      "sp_scode": "20",
      "sp_sxk": "",
      "sp_type": 0,
      "spe_id": 1181,
      "special_group": 0,
      "special_id": 37269,
      "spname": "海洋油气工程",
      "year": 2023,
      "zslx_name": "-",
      "data_type": "special"
    },
    {
      "average": 605,
      "doublehigh": 0,
      "dual_class_name": "",
      "first_km": 0,
      "id": "gkspecialscore2023789549",
      "info": "",
      "is_score_range": 2,
      "is_top": 2,
      "level2_name": "工学",
      "level3_name": "材料类",
      "local_batch_name": "本科一批",
      "local_province_name": "河南",
      "local_type_name": "理科",
      "max": 607,
      "min": 603,
      "min_range": "",
      "min_rank_range": "",
      "min_section": 19849,
      "name": "中国石油大学（北京）",
      "proscore": 514,
      "remark": "",
      "school_id": 832,
      "sg_fxk": "",
      "sg_info": "",
      "sg_name": "",
      "sg_sxk": "",
      "sg_type": 0,
      "single": "",
      "sp_fxk": "",
      "sp_info": "",
      "sp_name": "材料科学与工程",
      "sp_scode": "07",
      "sp_sxk": "",
      "sp_type": 0,
      "spe_id": 155,
      "special_group": 0,
      "special_id": 37277,
      "spname": "材料科学与工程",
      "year": 2023,
      "zslx_name": "-",
      "data_type": "special"
    },
    {
      "average": 603,
      "doublehigh": 0,
      "dual_class_name": "",
      "first_km": 0,
      "id": "gkspecialscore2023789560",
      "info": "（阿语复合人才实验班）",
      "is_score_range": 2,
      "is_top": 2,
      "level2_name": "工学",
      "level3_name": "矿业类",
      "local_batch_name": "本科一批",
      "local_province_name": "河南",
      "local_type_name": "理科",
      "max": 606,
      "min": 602,
      "min_range": "",
      "min_rank_range": "",
      "min_section": 20418,
      "name": "中国石油大学（北京）",
      "proscore": 514,
      "remark": "",
      "school_id": 832,
      "sg_fxk": "",
      "sg_info": "",
      "sg_name": "",
      "sg_sxk": "",
      "sg_type": 0,
      "single": "",
      "sp_fxk": "",
      "sp_info": "",
      "sp_name": "石油工程",
      "sp_scode": "18",
      "sp_sxk": "",
      "sp_type": 0,
      "spe_id": 193,
      "special_group": 0,
      "special_id": 37264,
      "spname": "石油工程（阿语复合人才实验班）",
      "year": 2023,
      "zslx_name": "-",
      "data_type": "special"
    },
    {
      "average": 603,
      "doublehigh": 0,
      "dual_class_name": "",
      "first_km": 0,
      "id": "gkspecialscore2023789557",
      "info": "（包含专业:化学工程与工艺，能源化学工程）",
      "is_score_range": 2,
      "is_top": 2,
      "level2_name": "工学",
      "level3_name": "化工与制药类",
      "local_batch_name": "本科一批",
      "local_province_name": "河南",
      "local_type_name": "理科",
      "max": 609,
      "min": 602,
      "min_range": "",
      "min_rank_range": "",
      "min_section": 20418,
      "name": "中国石油大学（北京）",
      "proscore": 514,
      "remark": "",
      "school_id": 832,
      "sg_fxk": "",
      "sg_info": "",
      "sg_name": "",
      "sg_sxk": "",
      "sg_type": 0,
      "single": "",
      "sp_fxk": "",
      "sp_info": "",
      "sp_name": "化工与制药类",
      "sp_scode": "15",
      "sp_sxk": "",
      "sp_type": 0,
      "spe_id": 1356,
      "special_group": 0,
      "special_id": 109429,
      "spname": "化工与制药类（包含专业:化学工程与工艺，能源化学工程）",
      "year": 2023,
      "zslx_name": "-",
      "data_type": "special"
    },
    {
      "average": 604,
      "doublehigh": 0,
      "dual_class_name": "",
      "first_km": 0,
      "id": "gkspecialscore2023789548",
      "info": "",
      "is_score_range": 2,
      "is_top": 2,
      "level2_name": "工学",
      "level3_name": "机械类",
      "local_batch_name": "本科一批",
      "local_province_name": "河南",
      "local_type_name": "理科",
      "max": 608,
      "min": 602,
      "min_range": "",
      "min_rank_range": "",
      "min_section": 20418,
      "name": "中国石油大学（北京）",
      "proscore": 514,
      "remark": "",
      "school_id": 832,
      "sg_fxk": "",
      "sg_info": "",
      "sg_name": "",
      "sg_sxk": "",
      "sg_type": 0,
      "single": "",
      "sp_fxk": "",
      "sp_info": "",
      "sp_name": "过程装备与控制工程",
      "sp_scode": "06",
      "sp_sxk": "",
      "sp_type": 0,
      "spe_id": 151,
      "special_group": 0,
      "special_id": 37279,
      "spname": "过程装备与控制工程",
      "year": 2023,
      "zslx_name": "-",
      "data_type": "special"
    },
    {
      "average": 602,
      "doublehigh": 0,
      "dual_class_name": "",
      "first_km": 0,
      "id": "gkspecialscore2023789546",
      "info": "（包含专业:勘查技术与工程，地球物理学）",
      "is_score_range": 2,
      "is_top": 2,
      "level2_name": "理学",
      "level3_name": "地球物理学类",
      "local_batch_name": "本科一批",
      "local_province_name": "河南",
      "local_type_name": "理科",
      "max": 603,
      "min": 602,
      "min_range": "",
      "min_rank_range": "",
      "min_section": 20418,
      "name": "中国石油大学（北京）",
      "proscore": 514,
      "remark": "",
      "school_id": 832,
      "sg_fxk": "",
      "sg_info": "",
      "sg_name": "",
      "sg_sxk": "",
      "sg_type": 0,
      "single": "",
      "sp_fxk": "",
      "sp_info": "",
      "sp_name": "地球物理学类",
      "sp_scode": "04",
      "sp_sxk": "",
      "sp_type": 0,
      "spe_id": 1339,
      "special_group": 0,
      "special_id": 1368183,
      "spname": "地球物理学类（包含专业:勘查技术与工程，地球物理学）",
      "year": 2023,
      "zslx_name": "-",
      "data_type": "special"
    },
    {
      "average": 602,
      "doublehigh": 0,
      "dual_class_name": "",
      "first_km": 0,
      "id": "gkspecialscore2023789543",
      "info": "（包含专业:能源经济，金融学）",
      "is_score_range": 2,
      "is_top": 2,
      "level2_name": "经济学",
      "level3_name": "经济学类",
      "local_batch_name": "本科一批",
      "local_province_name": "河南",
      "local_type_name": "理科",
      "max": 605,
      "min": 601,
      "min_range": "",
      "min_rank_range": "",
      "min_section": 21021,
      "name": "中国石油大学（北京）",
      "proscore": 514,
      "remark": "",
      "school_id": 832,
      "sg_fxk": "",
      "sg_info": "",
      "sg_name": "",
      "sg_sxk": "",
      "sg_type": 0,
      "single": "",
      "sp_fxk": "",
      "sp_info": "",
      "sp_name": "经济学类",
      "sp_scode": "01",
      "sp_sxk": "",
      "sp_type": 0,
      "spe_id": 1316,
      "special_group": 0,
      "special_id": 109417,
      "spname": "经济学类（包含专业:能源经济，金融学）",
      "year": 2023,
      "zslx_name": "-",
      "data_type": "special"
    },
    {
      "average": 627,
      "doublehigh": 0,
      "dual_class_name": "",
      "first_km": 0,
      "id": "gkspecialscore20241326654",
      "info": "（碳中和能源创新班）",
      "is_score_range": 2,
      "is_top": 2,
      "level2_name": "工学",
      "level3_name": "矿业类",
      "local_batch_name": "本科一批",
      "local_province_name": "河南",
      "local_type_name": "理科",
      "max": 629,
      "min": 624,
      "min_range": "",
      "min_rank_range": "",
      "min_section": 10962,
      "name": "中国石油大学（北京）",
      "proscore": 511,
      "remark": "",
      "school_id": 832,
      "sg_fxk": "",
      "sg_info": "",
      "sg_name": "",
      "sg_sxk": "",
      "sg_type": 0,
      "single": "",
      "sp_fxk": "",
      "sp_info": "",
      "sp_name": "石油工程",
      "sp_scode": "20",
      "sp_sxk": "",
      "sp_type": 0,
      "spe_id": 193,
      "special_group": 0,
      "special_id": 37264,
      "spname": "石油工程（碳中和能源创新班）",
      "year": 2024,
      "zslx_name": "-",
      "data_type": "special"
    },
    {
      "average": 624,
      "doublehigh": 0,
      "dual_class_name": "",
      "first_km": 0,
      "id": "gkspecialscore20241326649",
      "info": "",
      "is_score_range": 2,
      "is_top": 2,
      "level2_name": "工学",
      "level3_name": "计算机类",
      "local_batch_name": "本科一批",
      "local_province_name": "河南",
      "local_type_name": "理科",
      "max": 627,
      "min": 623,
      "min_range": "",
      "min_rank_range": "",
      "min_section": 11363,
      "name": "中国石油大学（北京）",
      "proscore": 511,
      "remark": "",
      "school_id": 832,
      "sg_fxk": "",
      "sg_info": "",
      "sg_name": "",
      "sg_sxk": "",
      "sg_type": 0,
      "single": "",
      "sp_fxk": "",
      "sp_info": "",
      "sp_name": "计算机科学与技术",
      "sp_scode": "15",
      "sp_sxk": "",
      "sp_type": 0,
      "spe_id": 172,
      "special_group": 0,
      "special_id": 37282,
      "spname": "计算机科学与技术",
      "year": 2024,
      "zslx_name": "-",
      "data_type": "special"
    },
    {
      "average": 622,
      "doublehigh": 0,
      "dual_class_name": "",
      "first_km": 0,
      "id": "gkspecialscore20241326647",
      "info": "",
      "is_score_range": 2,
      "is_top": 2,
      "level2_name": "工学",
      "level3_name": "电子信息类",
      "local_batch_name": "本科一批",
      "local_province_name": "河南",
      "local_type_name": "理科",
      "max": 622,
      "min": 621,
      "min_range": "",
      "min_rank_range": "",
      "min_section": 12204,
      "name": "中国石油大学（北京）",
      "proscore": 511,
      "remark": "",
      "school_id": 832,
      "sg_fxk": "",
      "sg_info": "",
      "sg_name": "",
      "sg_sxk": "",
      "sg_type": 0,
      "single": "",
      "sp_fxk": "",
      "sp_info": "",
      "sp_name": "人工智能",
      "sp_scode": "13",
      "sp_sxk": "",
      "sp_type": 0,
      "spe_id": 8387,
      "special_group": 0,
      "special_id": 1129617,
      "spname": "人工智能",
      "year": 2024,
      "zslx_name": "-",
      "data_type": "special"
    },
    {
      "average": 621,
      "doublehigh": 0,
      "dual_class_name": "",
      "first_km": 0,
      "id": "gkspecialscore20241326646",
      "info": "",
      "is_score_range": 2,
      "is_top": 2,
      "level2_name": "工学",
      "level3_name": "电子信息类",
      "local_batch_name": "本科一批",
      "local_province_name": "河南",
      "local_type_name": "理科",
      "max": 621,
      "min": 620,
      "min_range": "",
      "min_rank_range": "",
      "min_section": 12607,
      "name": "中国石油大学（北京）",
      "proscore": 511,
      "remark": "",
      "school_id": 832,
      "sg_fxk": "",
      "sg_info": "",
      "sg_name": "",
      "sg_sxk": "",
      "sg_type": 0,
      "single": "",
      "sp_fxk": "",
      "sp_info": "",
      "sp_name": "电子信息工程",
      "sp_scode": "12",
      "sp_sxk": "",
      "sp_type": 0,
      "spe_id": 165,
      "special_group": 0,
      "special_id": 37281,
      "spname": "电子信息工程",
      "year": 2024,
      "zslx_name": "-",
      "data_type": "special"
    },
    {
      "average": 619,
      "doublehigh": 0,
      "dual_class_name": "",
      "first_km": 0,
      "id": "gkspecialscore20241326648",
      "info": "",
      "is_score_range": 2,
      "is_top": 2,
      "level2_name": "工学",
      "level3_name": "自动化类",
      "local_batch_name": "本科一批",
      "local_province_name": "河南",
      "local_type_name": "理科",
      "max": 620,
      "min": 618,
      "min_range": "",
      "min_rank_range": "",
      "min_section": 13475,
      "name": "中国石油大学（北京）",
      "proscore": 511,
      "remark": "",
      "school_id": 832,
      "sg_fxk": "",
      "sg_info": "",
      "sg_name": "",
      "sg_sxk": "",
      "sg_type": 0,
      "single": "",
      "sp_fxk": "",
      "sp_info": "",
      "sp_name": "自动化",
      "sp_scode": "14",
      "sp_sxk": "",
      "sp_type": 0,
      "spe_id": 171,
      "special_group": 0,
      "special_id": 37280,
      "spname": "自动化",
      "year": 2024,
      "zslx_name": "-",
      "data_type": "special"
    },
    {
      "average": 617,
      "doublehigh": 0,
      "dual_class_name": "",
      "first_km": 0,
      "id": "gkspecialscore20241326644",
      "info": "",
      "is_score_range": 2,
      "is_top": 2,
      "level2_name": "工学",
      "level3_name": "能源动力类",
      "local_batch_name": "本科一批",
      "local_province_name": "河南",
      "local_type_name": "理科",
      "max": 618,
      "min": 617,
      "min_range": "",
      "min_rank_range": "",
      "min_section": 13941,
      "name": "中国石油大学（北京）",
      "proscore": 511,
      "remark": "",
      "school_id": 832,
      "sg_fxk": "",
      "sg_info": "",
      "sg_name": "",
      "sg_sxk": "",
      "sg_type": 0,
      "single": "",
      "sp_fxk": "",
      "sp_info": "",
      "sp_name": "新能源科学与工程",
      "sp_scode": "10",
      "sp_sxk": "",
      "sp_type": 0,
      "spe_id": 1152,
      "special_group": 0,
      "special_id": 174517,
      "spname": "新能源科学与工程",
      "year": 2024,
      "zslx_name": "-",
      "data_type": "special"
    },
    {
      "average": 616,
      "doublehigh": 0,
      "dual_class_name": "",
      "first_km": 0,
      "id": "gkspecialscore20241326645",
      "info": "",
      "is_score_range": 2,
      "is_top": 2,
      "level2_name": "工学",
      "level3_name": "能源动力类",
      "local_batch_name": "本科一批",
      "local_province_name": "河南",
      "local_type_name": "理科",
      "max": 616,
      "min": 616,
      "min_range": "",
      "min_rank_range": "",
      "min_section": 14396,
      "name": "中国石油大学（北京）",
      "proscore": 511,
      "remark": "",
      "school_id": 832,
      "sg_fxk": "",
      "sg_info": "",
      "sg_name": "",
      "sg_sxk": "",
      "sg_type": 0,
      "single": "",
      "sp_fxk": "",
      "sp_info": "",
      "sp_name": "储能科学与工程",
      "sp_scode": "11",
      "sp_sxk": "",
      "sp_type": 0,
      "spe_id": 8689,
      "special_group": 0,
      "special_id": 1500080,
      "spname": "储能科学与工程",
      "year": 2024,
      "zslx_name": "-",
      "data_type": "special"
    },
    {
      "average": 616,
      "doublehigh": 0,
      "dual_class_name": "",
      "first_km": 0,
      "id": "gkspecialscore20241326643",
      "info": "",
      "is_score_range": 2,
      "is_top": 2,
      "level2_name": "工学",
      "level3_name": "能源动力类",
      "local_batch_name": "本科一批",
      "local_province_name": "河南",
      "local_type_name": "理科",
      "max": 617,
      "min": 615,
      "min_range": "",
      "min_rank_range": "",
      "min_section": 14891,
      "name": "中国石油大学（北京）",
      "proscore": 511,
      "remark": "",
      "school_id": 832,
      "sg_fxk": "",
      "sg_info": "",
      "sg_name": "",
      "sg_sxk": "",
      "sg_type": 0,
      "single": "",
      "sp_fxk": "",
      "sp_info": "",
      "sp_name": "能源与动力工程",
      "sp_scode": "09",
      "sp_sxk": "",
      "sp_type": 0,
      "spe_id": 163,
      "special_group": 0,
      "special_id": 37303,
      "spname": "能源与动力工程",
      "year": 2024,
      "zslx_name": "-",
      "data_type": "special"
    },
    {
      "average": 617,
      "doublehigh": 0,
      "dual_class_name": "",
      "first_km": 0,
      "id": "gkspecialscore20241326640",
      "info": "（包含专业:机器人工程、机械设计制造及其自动化）",
      "is_score_range": 2,
      "is_top": 2,
      "level2_name": "工学",
      "level3_name": "机械类",
      "local_batch_name": "本科一批",
      "local_province_name": "河南",
      "local_type_name": "理科",
      "max": 618,
      "min": 615,
      "min_range": "",
      "min_rank_range": "",
      "min_section": 14891,
      "name": "中国石油大学（北京）",
      "proscore": 511,
      "remark": "",
      "school_id": 832,
      "sg_fxk": "",
      "sg_info": "",
      "sg_name": "",
      "sg_sxk": "",
      "sg_type": 0,
      "single": "",
      "sp_fxk": "",
      "sp_info": "",
      "sp_name": "机械类",
      "sp_scode": "06",
      "sp_sxk": "",
      "sp_type": 0,
      "spe_id": 1345,
      "special_group": 0,
      "special_id": 109430,
      "spname": "机械类（包含专业:机器人工程、机械设计制造及其自动化）",
      "year": 2024,
      "zslx_name": "-",
      "data_type": "special"
    },
    {
      "average": 616,
      "doublehigh": 0,
      "dual_class_name": "",
      "first_km": 0,
      "id": "gkspecialscore20241326637",
      "info": "（包含专业:数学与应用数学、统计学）",
      "is_score_range": 2,
      "is_top": 2,
      "level2_name": "理学",
      "level3_name": "数学类",
      "local_batch_name": "本科一批",
      "local_province_name": "河南",
      "local_type_name": "理科",
      "max": 619,
      "min": 615,
      "min_range": "",
      "min_rank_range": "",
      "min_section": 14891,
      "name": "中国石油大学（北京）",
      "proscore": 511,
      "remark": "",
      "school_id": 832,
      "sg_fxk": "",
      "sg_info": "",
      "sg_name": "",
      "sg_sxk": "",
      "sg_type": 0,
      "single": "",
      "sp_fxk": "",
      "sp_info": "",
      "sp_name": "数学类",
      "sp_scode": "03",
      "sp_sxk": "",
      "sp_type": 0,
      "spe_id": 1332,
      "special_group": 0,
      "special_id": 727986,
      "spname": "数学类（包含专业:数学与应用数学、统计学）",
      "year": 2024,
      "zslx_name": "-",
      "data_type": "special"
    },
    {
      "average": 616,
      "doublehigh": 0,
      "dual_class_name": "",
      "first_km": 0,
      "id": "gkspecialscore20241326653",
      "info": "",
      "is_score_range": 2,
      "is_top": 2,
      "level2_name": "工学",
      "level3_name": "矿业类",
      "local_batch_name": "本科一批",
      "local_province_name": "河南",
      "local_type_name": "理科",
      "max": 619,
      "min": 614,
      "min_range": "",
      "min_rank_range": "",
      "min_section": 15402,
      "name": "中国石油大学（北京）",
      "proscore": 511,
      "remark": "",
      "school_id": 832,
      "sg_fxk": "",
      "sg_info": "",
      "sg_name": "",
      "sg_sxk": "",
      "sg_type": 0,
      "single": "",
      "sp_fxk": "",
      "sp_info": "",
      "sp_name": "石油工程",
      "sp_scode": "19",
      "sp_sxk": "",
      "sp_type": 0,
      "spe_id": 193,
      "special_group": 0,
      "special_id": 37264,
      "spname": "石油工程",
      "year": 2024,
      "zslx_name": "-",
      "data_type": "special"
    },
    {
      "average": 614,
      "doublehigh": 0,
      "dual_class_name": "",
      "first_km": 0,
      "id": "gkspecialscore20241326657",
      "info": "",
      "is_score_range": 2,
      "is_top": 2,
      "level2_name": "工学",
      "level3_name": "矿业类",
      "local_batch_name": "本科一批",
      "local_province_name": "河南",
      "local_type_name": "理科",
      "max": 617,
      "min": 611,
      "min_range": "",
      "min_rank_range": "",
      "min_section": 16982,
      "name": "中国石油大学（北京）",
      "proscore": 511,
      "remark": "",
      "school_id": 832,
      "sg_fxk": "",
      "sg_info": "",
      "sg_name": "",
      "sg_sxk": "",
      "sg_type": 0,
      "single": "",
      "sp_fxk": "",
      "sp_info": "",
      "sp_name": "碳储科学与工程",
      "sp_scode": "23",
      "sp_sxk": "",
      "sp_type": 0,
      "spe_id": 9336,
      "special_group": 0,
      "special_id": 1801709,
      "spname": "碳储科学与工程",
      "year": 2024,
      "zslx_name": "-",
      "data_type": "special"
    },
    {
      "average": 611,
      "doublehigh": 0,
      "dual_class_name": "",
      "first_km": 0,
      "id": "gkspecialscore20241326642",
      "info": "",
      "is_score_range": 2,
      "is_top": 2,
      "level2_name": "工学",
      "level3_name": "材料类",
      "local_batch_name": "本科一批",
      "local_province_name": "河南",
      "local_type_name": "理科",
      "max": 613,
      "min": 609,
      "min_range": "",
      "min_rank_range": "",
      "min_section": 18059,
      "name": "中国石油大学（北京）",
      "proscore": 511,
      "remark": "",
      "school_id": 832,
      "sg_fxk": "",
      "sg_info": "",
      "sg_name": "",
      "sg_sxk": "",
      "sg_type": 0,
      "single": "",
      "sp_fxk": "",
      "sp_info": "",
      "sp_name": "材料科学与工程",
      "sp_scode": "08",
      "sp_sxk": "",
      "sp_type": 0,
      "spe_id": 155,
      "special_group": 0,
      "special_id": 37277,
      "spname": "材料科学与工程",
      "year": 2024,
      "zslx_name": "-",
      "data_type": "special"
    },
    {
      "average": 609,
      "doublehigh": 0,
      "dual_class_name": "",
      "first_km": 0,
      "id": "gkspecialscore20241326660",
      "info": "",
      "is_score_range": 2,
      "is_top": 2,
      "level2_name": "管理学",
      "level3_name": "管理科学与工程类",
      "local_batch_name": "本科一批",
      "local_province_name": "河南",
      "local_type_name": "理科",
      "max": 609,
      "min": 608,
      "min_range": "",
      "min_rank_range": "",
      "min_section": 18642,
      "name": "中国石油大学（北京）",
      "proscore": 511,
      "remark": "",
      "school_id": 832,
      "sg_fxk": "",
      "sg_info": "",
      "sg_name": "",
      "sg_sxk": "",
      "sg_type": 0,
      "single": "",
      "sp_fxk": "",
      "sp_info": "",
      "sp_name": "信息管理与信息系统",
      "sp_scode": "26",
      "sp_sxk": "",
      "sp_type": 0,
      "spe_id": 293,
      "special_group": 0,
      "special_id": 37285,
      "spname": "信息管理与信息系统",
      "year": 2024,
      "zslx_name": "-",
      "data_type": "special"
    },
    {
      "average": 610,
      "doublehigh": 0,
      "dual_class_name": "",
      "first_km": 0,
      "id": "gkspecialscore20241326656",
      "info": "",
      "is_score_range": 2,
      "is_top": 2,
      "level2_name": "工学",
      "level3_name": "矿业类",
      "local_batch_name": "本科一批",
      "local_province_name": "河南",
      "local_type_name": "理科",
      "max": 613,
      "min": 608,
      "min_range": "",
      "min_rank_range": "",
      "min_section": 18642,
      "name": "中国石油大学（北京）",
      "proscore": 511,
      "remark": "",
      "school_id": 832,
      "sg_fxk": "",
      "sg_info": "",
      "sg_name": "",
      "sg_sxk": "",
      "sg_type": 0,
      "single": "",
      "sp_fxk": "",
      "sp_info": "",
      "sp_name": "海洋油气工程",
      "sp_scode": "22",
      "sp_sxk": "",
      "sp_type": 0,
      "spe_id": 1181,
      "special_group": 0,
      "special_id": 37269,
      "spname": "海洋油气工程",
      "year": 2024,
      "zslx_name": "-",
      "data_type": "special"
    },
    {
      "average": 612,
      "doublehigh": 0,
      "dual_class_name": "",
      "first_km": 0,
      "id": "gkspecialscore20241326655",
      "info": "",
      "is_score_range": 2,
      "is_top": 2,
      "level2_name": "工学",
      "level3_name": "矿业类",
      "local_batch_name": "本科一批",
      "local_province_name": "河南",
      "local_type_name": "理科",
      "max": 617,
      "min": 608,
      "min_range": "",
      "min_rank_range": "",
      "min_section": 18642,
      "name": "中国石油大学（北京）",
      "proscore": 511,
      "remark": "",
      "school_id": 832,
      "sg_fxk": "",
      "sg_info": "",
      "sg_name": "",
      "sg_sxk": "",
      "sg_type": 0,
      "single": "",
      "sp_fxk": "",
      "sp_info": "",
      "sp_name": "油气储运工程",
      "sp_scode": "21",
      "sp_sxk": "",
      "sp_type": 0,
      "spe_id": 195,
      "special_group": 0,
      "special_id": 37276,
      "spname": "油气储运工程",
      "year": 2024,
      "zslx_name": "-",
      "data_type": "special"
    },
    {
      "average": 614,
      "doublehigh": 0,
      "dual_class_name": "",
      "first_km": 0,
      "id": "gkspecialscore20241326652",
      "info": "（油气与清洁地质能源）",
      "is_score_range": 2,
      "is_top": 2,
      "level2_name": "工学",
      "level3_name": "地质类",
      "local_batch_name": "本科一批",
      "local_province_name": "河南",
      "local_type_name": "理科",
      "max": 618,
      "min": 608,
      "min_range": "",
      "min_rank_range": "",
      "min_section": 18642,
      "name": "中国石油大学（北京）",
      "proscore": 511,
      "remark": "",
      "school_id": 832,
      "sg_fxk": "",
      "sg_info": "",
      "sg_name": "",
      "sg_sxk": "",
      "sg_type": 0,
      "single": "",
      "sp_fxk": "",
      "sp_info": "",
      "sp_name": "资源勘查工程",
      "sp_scode": "18",
      "sp_sxk": "",
      "sp_type": 0,
      "spe_id": 191,
      "special_group": 0,
      "special_id": 37298,
      "spname": "资源勘查工程（油气与清洁地质能源）",
      "year": 2024,
      "zslx_name": "-",
      "data_type": "special"
    },
    {
      "average": 611,
      "doublehigh": 0,
      "dual_class_name": "",
      "first_km": 0,
      "id": "gkspecialscore20241326641",
      "info": "",
      "is_score_range": 2,
      "is_top": 2,
      "level2_name": "工学",
      "level3_name": "机械类",
      "local_batch_name": "本科一批",
      "local_province_name": "河南",
      "local_type_name": "理科",
      "max": 615,
      "min": 608,
      "min_range": "",
      "min_rank_range": "",
      "min_section": 18642,
      "name": "中国石油大学（北京）",
      "proscore": 511,
      "remark": "",
      "school_id": 832,
      "sg_fxk": "",
      "sg_info": "",
      "sg_name": "",
      "sg_sxk": "",
      "sg_type": 0,
      "single": "",
      "sp_fxk": "",
      "sp_info": "",
      "sp_name": "过程装备与控制工程",
      "sp_scode": "07",
      "sp_sxk": "",
      "sp_type": 0,
      "spe_id": 151,
      "special_group": 0,
      "special_id": 37279,
      "spname": "过程装备与控制工程",
      "year": 2024,
      "zslx_name": "-",
      "data_type": "special"
    },
    {
      "average": 609,
      "doublehigh": 0,
      "dual_class_name": "",
      "first_km": 0,
      "id": "gkspecialscore20241326638",
      "info": "",
      "is_score_range": 2,
      "is_top": 2,
      "level2_name": "理学",
      "level3_name": "化学类",
      "local_batch_name": "本科一批",
      "local_province_name": "河南",
      "local_type_name": "理科",
      "max": 611,
      "min": 607,
      "min_range": "",
      "min_rank_range": "",
      "min_section": 19256,
      "name": "中国石油大学（北京）",
      "proscore": 511,
      "remark": "",
      "school_id": 832,
      "sg_fxk": "",
      "sg_info": "",
      "sg_name": "",
      "sg_sxk": "",
      "sg_type": 0,
      "single": "",
      "sp_fxk": "",
      "sp_info": "",
      "sp_name": "应用化学",
      "sp_scode": "04",
      "sp_sxk": "",
      "sp_type": 0,
      "spe_id": 122,
      "special_group": 0,
      "special_id": 37273,
      "spname": "应用化学",
      "year": 2024,
      "zslx_name": "-",
      "data_type": "special"
    },
    {
      "average": 608,
      "doublehigh": 0,
      "dual_class_name": "",
      "first_km": 0,
      "id": "gkspecialscore20241326659",
      "info": "",
      "is_score_range": 2,
      "is_top": 2,
      "level2_name": "工学",
      "level3_name": "安全科学与工程类",
      "local_batch_name": "本科一批",
      "local_province_name": "河南",
      "local_type_name": "理科",
      "max": 610,
      "min": 606,
      "min_range": "",
      "min_rank_range": "",
      "min_section": 19869,
      "name": "中国石油大学（北京）",
      "proscore": 511,
      "remark": "",
      "school_id": 832,
      "sg_fxk": "",
      "sg_info": "",
      "sg_name": "",
      "sg_sxk": "",
      "sg_type": 0,
      "single": "",
      "sp_fxk": "",
      "sp_info": "",
      "sp_name": "安全工程",
      "sp_scode": "25",
      "sp_sxk": "",
      "sp_type": 0,
      "spe_id": 244,
      "special_group": 0,
      "special_id": 37307,
      "spname": "安全工程",
      "year": 2024,
      "zslx_name": "-",
      "data_type": "special"
    },
    {
      "average": 610,
      "doublehigh": 0,
      "dual_class_name": "",
      "first_km": 0,
      "id": "gkspecialscore20241326650",
      "info": "（包含专业：化学工程与工艺、能源化学工程）",
      "is_score_range": 2,
      "is_top": 2,
      "level2_name": "工学",
      "level3_name": "化工与制药类",
      "local_batch_name": "本科一批",
      "local_province_name": "河南",
      "local_type_name": "理科",
      "max": 614,
      "min": 606,
      "min_range": "",
      "min_rank_range": "",
      "min_section": 19869,
      "name": "中国石油大学（北京）",
      "proscore": 511,
      "remark": "",
      "school_id": 832,
      "sg_fxk": "",
      "sg_info": "",
      "sg_name": "",
      "sg_sxk": "",
      "sg_type": 0,
      "single": "",
      "sp_fxk": "",
      "sp_info": "",
      "sp_name": "化工与制药类",
      "sp_scode": "16",
      "sp_sxk": "",
      "sp_type": 0,
      "spe_id": 1356,
      "special_group": 0,
      "special_id": 109429,
      "spname": "化工与制药类（包含专业：化学工程与工艺、能源化学工程）",
      "year": 2024,
      "zslx_name": "-",
      "data_type": "special"
    },
    {
      "average": 608,
      "doublehigh": 0,
      "dual_class_name": "",
      "first_km": 0,
      "id": "gkspecialscore20241326639",
      "info": "（智能探测）",
      "is_score_range": 2,
      "is_top": 2,
      "level2_name": "理学",
      "level3_name": "地球物理学类",
      "local_batch_name": "本科一批",
      "local_province_name": "河南",
      "local_type_name": "理科",
      "max": 609,
      "min": 606,
      "min_range": "",
      "min_rank_range": "",
      "min_section": 19869,
      "name": "中国石油大学（北京）",
      "proscore": 511,
      "remark": "",
      "school_id": 832,
      "sg_fxk": "",
      "sg_info": "",
      "sg_name": "",
      "sg_sxk": "",
      "sg_type": 0,
      "single": "",
      "sp_fxk": "",
      "sp_info": "",
      "sp_name": "地球物理学",
      "sp_scode": "05",
      "sp_sxk": "",
      "sp_type": 0,
      "spe_id": 132,
      "special_group": 0,
      "special_id": 37295,
      "spname": "地球物理学（智能探测）",
      "year": 2024,
      "zslx_name": "-",
      "data_type": "special"
    },
    {
      "average": 609,
      "doublehigh": 0,
      "dual_class_name": "",
      "first_km": 0,
      "id": "gkspecialscore20241326636",
      "info": "（新能源工程双学士学位）",
      "is_score_range": 2,
      "is_top": 2,
      "level2_name": "经济学",
      "level3_name": "经济学类",
      "local_batch_name": "本科一批",
      "local_province_name": "河南",
      "local_type_name": "理科",
      "max": 616,
      "min": 606,
      "min_range": "",
      "min_rank_range": "",
      "min_section": 19869,
      "name": "中国石油大学（北京）",
      "proscore": 511,
      "remark": "",
      "school_id": 832,
      "sg_fxk": "",
      "sg_info": "",
      "sg_name": "",
      "sg_sxk": "",
      "sg_type": 0,
      "single": "",
      "sp_fxk": "",
      "sp_info": "",
      "sp_name": "能源经济",
      "sp_scode": "02",
      "sp_sxk": "",
      "sp_type": 0,
      "spe_id": 1102,
      "special_group": 0,
      "special_id": 37317,
      "spname": "能源经济（新能源工程双学士学位）",
      "year": 2024,
      "zslx_name": "-",
      "data_type": "special"
    },
    {
      "average": 605,
      "doublehigh": 0,
      "dual_class_name": "",
      "first_km": 0,
      "id": "gkspecialscore20241326658",
      "info": "（包含专业：环境工程、环境科学）",
      "is_score_range": 2,
      "is_top": 2,
      "level2_name": "工学",
      "level3_name": "环境科学与工程类",
      "local_batch_name": "本科一批",
      "local_province_name": "河南",
      "local_type_name": "理科",
      "max": 605,
      "min": 605,
      "min_range": "",
      "min_rank_range": "",
      "min_section": 20456,
      "name": "中国石油大学（北京）",
      "proscore": 511,
      "remark": "",
      "school_id": 832,
      "sg_fxk": "",
      "sg_info": "",
      "sg_name": "",
      "sg_sxk": "",
      "sg_type": 0,
      "single": "",
      "sp_fxk": "",
      "sp_info": "",
      "sp_name": "环境科学与工程类",
      "sp_scode": "24",
      "sp_sxk": "",
      "sp_type": 0,
      "spe_id": 1368,
      "special_group": 0,
      "special_id": 204103,
      "spname": "环境科学与工程类（包含专业：环境工程、环境科学）",
      "year": 2024,
      "zslx_name": "-",
      "data_type": "special"
    },
    {
      "average": 607,
      "doublehigh": 0,
      "dual_class_name": "",
      "first_km": 0,
      "id": "gkspecialscore20241326651",
      "info": "",
      "is_score_range": 2,
      "is_top": 2,
      "level2_name": "工学",
      "level3_name": "地质类",
      "local_batch_name": "本科一批",
      "local_province_name": "河南",
      "local_type_name": "理科",
      "max": 607,
      "min": 605,
      "min_range": "",
      "min_rank_range": "",
      "min_section": 20456,
      "name": "中国石油大学（北京）",
      "proscore": 511,
      "remark": "",
      "school_id": 832,
      "sg_fxk": "",
      "sg_info": "",
      "sg_name": "",
      "sg_sxk": "",
      "sg_type": 0,
      "single": "",
      "sp_fxk": "",
      "sp_info": "",
      "sp_name": "勘查技术与工程",
      "sp_scode": "17",
      "sp_sxk": "",
      "sp_type": 0,
      "spe_id": 190,
      "special_group": 0,
      "special_id": 37275,
      "spname": "勘查技术与工程",
      "year": 2024,
      "zslx_name": "-",
      "data_type": "special"
    },
    {
      "average": 606,
      "doublehigh": 0,
      "dual_class_name": "",
      "first_km": 0,
      "id": "gkspecialscore20241326661",
      "info": "（包含专业:会计学、财务管理、市场营销）",
      "is_score_range": 2,
      "is_top": 2,
      "level2_name": "管理学",
      "level3_name": "工商管理类",
      "local_batch_name": "本科一批",
      "local_province_name": "河南",
      "local_type_name": "理科",
      "max": 607,
      "min": 604,
      "min_range": "",
      "min_rank_range": "",
      "min_section": 21039,
      "name": "中国石油大学（北京）",
      "proscore": 511,
      "remark": "",
      "school_id": 832,
      "sg_fxk": "",
      "sg_info": "",
      "sg_name": "",
      "sg_sxk": "",
      "sg_type": 0,
      "single": "",
      "sp_fxk": "",
      "sp_info": "",
      "sp_name": "工商管理类",
      "sp_scode": "27",
      "sp_sxk": "",
      "sp_type": 0,
      "spe_id": 1394,
      "special_group": 0,
      "special_id": 109418,
      "spname": "工商管理类（包含专业:会计学、财务管理、市场营销）",
      "year": 2024,
      "zslx_name": "-",
      "data_type": "special"
    },
    {
      "average": 605,
      "doublehigh": 0,
      "dual_class_name": "",
      "first_km": 0,
      "id": "gkspecialscore20241326635",
      "info": "（包含专业:能源经济、金融学）",
      "is_score_range": 2,
      "is_top": 2,
      "level2_name": "经济学",
      "level3_name": "经济学类",
      "local_batch_name": "本科一批",
      "local_province_name": "河南",
      "local_type_name": "理科",
      "max": 605,
      "min": 604,
      "min_range": "",
      "min_rank_range": "",
      "min_section": 21039,
      "name": "中国石油大学（北京）",
      "proscore": 511,
      "remark": "",
      "school_id": 832,
      "sg_fxk": "",
      "sg_info": "",
      "sg_name": "",
      "sg_sxk": "",
      "sg_type": 0,
      "single": "",
      "sp_fxk": "",
      "sp_info": "",
      "sp_name": "经济学类",
      "sp_scode": "01",
      "sp_sxk": "",
      "sp_type": 0,
      "spe_id": 1316,
      "special_group": 0,
      "special_id": 109417,
      "spname": "经济学类（包含专业:能源经济、金融学）",
      "year": 2024,
      "zslx_name": "-",
      "data_type": "special"
    },
    {
      "average": 586,
      "doublehigh": 0,
      "dual_class_name": "",
      "first_km": 0,
      "id": "gkspecialscore20241317538",
      "info": "",
      "is_score_range": 2,
      "is_top": 2,
      "level2_name": "法学",
      "level3_name": "马克思主义理论类",
      "local_batch_name": "本科一批",
      "local_province_name": "河南",
      "local_type_name": "文科",
      "max": 588,
      "min": 585,
      "min_range": "",
      "min_rank_range": "",
      "min_section": 3808,
      "name": "中国石油大学（北京）",
      "proscore": 521,
      "remark": "",
      "school_id": 832,
      "sg_fxk": "",
      "sg_info": "",
      "sg_name": "",
      "sg_sxk": "",
      "sg_type": 0,
      "single": "",
      "sp_fxk": "",
      "sp_info": "",
      "sp_name": "思想政治教育",
      "sp_scode": "01",
      "sp_sxk": "",
      "sp_type": 0,
      "spe_id": 23,
      "special_group": 0,
      "special_id": 1129615,
      "spname": "思想政治教育",
      "year": 2024,
      "zslx_name": "-",
      "data_type": "special"
    },
    {
      "average": 582,
      "doublehigh": 0,
      "dual_class_name": "",
      "first_km": 0,
      "id": "gkspecialscore20241317539",
      "info": "（全球能源治理）（只招英语语种考生）",
      "is_score_range": 2,
      "is_top": 2,
      "level2_name": "文学",
      "level3_name": "外国语言文学类",
      "local_batch_name": "本科一批",
      "local_province_name": "河南",
      "local_type_name": "文科",
      "max": 583,
      "min": 581,
      "min_range": "",
      "min_rank_range": "",
      "min_section": 4526,
      "name": "中国石油大学（北京）",
      "proscore": 521,
      "remark": "",
      "school_id": 832,
      "sg_fxk": "",
      "sg_info": "",
      "sg_name": "",
      "sg_sxk": "",
      "sg_type": 0,
      "single": "",
      "sp_fxk": "",
      "sp_info": "",
      "sp_name": "英语",
      "sp_scode": "02",
      "sp_sxk": "",
      "sp_type": 0,
      "spe_id": 45,
      "special_group": 0,
      "special_id": 37290,
      "spname": "英语（全球能源治理）（只招英语语种考生）",
      "year": 2024,
      "zslx_name": "-",
      "data_type": "special"
    },
    {
      "average": 656,
      "doublehigh": 0,
      "dual_class_name": "",
      "first_km": 70000,
      "id": "gkspecialscore20251040933",
      "info": "（碳中和能源创新班）",
      "is_score_range": 2,
      "is_top": 2,
      "level2_name": "工学",
      "level3_name": "矿业类",
      "local_batch_name": "本科批",
      "local_province_name": "河南",
      "local_type_name": "物理类",
      "max": 658,
      "min": 654,
      "min_range": "",
      "min_rank_range": "",
      "min_section": 6779,
      "name": "中国石油大学（北京）",
      "proscore": 427,
      "remark": "",
      "school_id": 832,
      "sg_fxk": "70000",
      "sg_info": "首选物理，再选化学",
      "sg_name": "（101）",
      "sg_sxk": "70001",
      "sg_type": 80003,
      "single": "",
      "sp_fxk": "",
      "sp_info": "",
      "sp_name": "石油工程",
      "sp_scode": "",
      "sp_sxk": "",
      "sp_type": 0,
      "spe_id": 193,
      "special_group": 503078,
      "special_id": 37264,
      "spname": "石油工程（碳中和能源创新班）",
      "year": 2025,
      "zslx_name": "-",
      "data_type": "special"
    },
    {
      "average": 644,
      "doublehigh": 0,
      "dual_class_name": "",
      "first_km": 70000,
      "id": "gkspecialscore20251040932",
      "info": "",
      "is_score_range": 2,
      "is_top": 2,
      "level2_name": "工学",
      "level3_name": "计算机类",
      "local_batch_name": "本科批",
      "local_province_name": "河南",
      "local_type_name": "物理类",
      "max": 647,
      "min": 643,
      "min_range": "",
      "min_rank_range": "",
      "min_section": 11370,
      "name": "中国石油大学（北京）",
      "proscore": 427,
      "remark": "",
      "school_id": 832,
      "sg_fxk": "70000",
      "sg_info": "首选物理，再选化学",
      "sg_name": "（101）",
      "sg_sxk": "70001",
      "sg_type": 80003,
      "single": "",
      "sp_fxk": "",
      "sp_info": "",
      "sp_name": "计算机科学与技术",
      "sp_scode": "",
      "sp_sxk": "",
      "sp_type": 0,
      "spe_id": 172,
      "special_group": 503078,
      "special_id": 37282,
      "spname": "计算机科学与技术",
      "year": 2025,
      "zslx_name": "-",
      "data_type": "special"
    },
    {
      "average": 642,
      "doublehigh": 0,
      "dual_class_name": "",
      "first_km": 70000,
      "id": "gkspecialscore20251040931",
      "info": "",
      "is_score_range": 2,
      "is_top": 2,
      "level2_name": "工学",
      "level3_name": "自动化类",
      "local_batch_name": "本科批",
      "local_province_name": "河南",
      "local_type_name": "物理类",
      "max": 642,
      "min": 641,
      "min_range": "",
      "min_rank_range": "",
      "min_section": 12353,
      "name": "中国石油大学（北京）",
      "proscore": 427,
      "remark": "",
      "school_id": 832,
      "sg_fxk": "70000",
      "sg_info": "首选物理，再选化学",
      "sg_name": "（101）",
      "sg_sxk": "70001",
      "sg_type": 80003,
      "single": "",
      "sp_fxk": "",
      "sp_info": "",
      "sp_name": "自动化",
      "sp_scode": "",
      "sp_sxk": "",
      "sp_type": 0,
      "spe_id": 171,
      "special_group": 503078,
      "special_id": 37280,
      "spname": "自动化",
      "year": 2025,
      "zslx_name": "-",
      "data_type": "special"
    },
    {
      "average": 642,
      "doublehigh": 0,
      "dual_class_name": "",
      "first_km": 70000,
      "id": "gkspecialscore20251040930",
      "info": "",
      "is_score_range": 2,
      "is_top": 2,
      "level2_name": "工学",
      "level3_name": "电子信息类",
      "local_batch_name": "本科批",
      "local_province_name": "河南",
      "local_type_name": "物理类",
      "max": 644,
      "min": 640,
      "min_range": "",
      "min_rank_range": "",
      "min_section": 12870,
      "name": "中国石油大学（北京）",
      "proscore": 427,
      "remark": "",
      "school_id": 832,
      "sg_fxk": "70000",
      "sg_info": "首选物理，再选化学",
      "sg_name": "（101）",
      "sg_sxk": "70001",
      "sg_type": 80003,
      "single": "",
      "sp_fxk": "",
      "sp_info": "",
      "sp_name": "电子信息工程",
      "sp_scode": "",
      "sp_sxk": "",
      "sp_type": 0,
      "spe_id": 165,
      "special_group": 503078,
      "special_id": 37281,
      "spname": "电子信息工程",
      "year": 2025,
      "zslx_name": "-",
      "data_type": "special"
    },
    {
      "average": 640,
      "doublehigh": 0,
      "dual_class_name": "",
      "first_km": 70000,
      "id": "gkspecialscore20251040929",
      "info": "",
      "is_score_range": 2,
      "is_top": 2,
      "level2_name": "工学",
      "level3_name": "电子信息类",
      "local_batch_name": "本科批",
      "local_province_name": "河南",
      "local_type_name": "物理类",
      "max": 641,
      "min": 639,
      "min_range": "",
      "min_rank_range": "",
      "min_section": 13404,
      "name": "中国石油大学（北京）",
      "proscore": 427,
      "remark": "",
      "school_id": 832,
      "sg_fxk": "70000",
      "sg_info": "首选物理，再选化学",
      "sg_name": "（101）",
      "sg_sxk": "70001",
      "sg_type": 80003,
      "single": "",
      "sp_fxk": "",
      "sp_info": "",
      "sp_name": "人工智能",
      "sp_scode": "",
      "sp_sxk": "",
      "sp_type": 0,
      "spe_id": 8387,
      "special_group": 503078,
      "special_id": 1129617,
      "spname": "人工智能",
      "year": 2025,
      "zslx_name": "-",
      "data_type": "special"
    },
    {
      "average": 638,
      "doublehigh": 0,
      "dual_class_name": "",
      "first_km": 70000,
      "id": "gkspecialscore20251040928",
      "info": "",
      "is_score_range": 2,
      "is_top": 2,
      "level2_name": "工学",
      "level3_name": "能源动力类",
      "local_batch_name": "本科批",
      "local_province_name": "河南",
      "local_type_name": "物理类",
      "max": 639,
      "min": 638,
      "min_range": "",
      "min_rank_range": "",
      "min_section": 13941,
      "name": "中国石油大学（北京）",
      "proscore": 427,
      "remark": "",
      "school_id": 832,
      "sg_fxk": "70000",
      "sg_info": "首选物理，再选化学",
      "sg_name": "（101）",
      "sg_sxk": "70001",
      "sg_type": 80003,
      "single": "",
      "sp_fxk": "",
      "sp_info": "",
      "sp_name": "新能源科学与工程",
      "sp_scode": "",
      "sp_sxk": "",
      "sp_type": 0,
      "spe_id": 1152,
      "special_group": 503078,
      "special_id": 174517,
      "spname": "新能源科学与工程",
      "year": 2025,
      "zslx_name": "-",
      "data_type": "special"
    },
    {
      "average": 640,
      "doublehigh": 0,
      "dual_class_name": "",
      "first_km": 70000,
      "id": "gkspecialscore20251040927",
      "info": "",
      "is_score_range": 2,
      "is_top": 2,
      "level2_name": "工学",
      "level3_name": "矿业类",
      "local_batch_name": "本科批",
      "local_province_name": "河南",
      "local_type_name": "物理类",
      "max": 643,
      "min": 638,
      "min_range": "",
      "min_rank_range": "",
      "min_section": 13941,
      "name": "中国石油大学（北京）",
      "proscore": 427,
      "remark": "",
      "school_id": 832,
      "sg_fxk": "70000",
      "sg_info": "首选物理，再选化学",
      "sg_name": "（101）",
      "sg_sxk": "70001",
      "sg_type": 80003,
      "single": "",
      "sp_fxk": "",
      "sp_info": "",
      "sp_name": "石油工程",
      "sp_scode": "",
      "sp_sxk": "",
      "sp_type": 0,
      "spe_id": 193,
      "special_group": 503078,
      "special_id": 37264,
      "spname": "石油工程",
      "year": 2025,
      "zslx_name": "-",
      "data_type": "special"
    },
    {
      "average": 639,
      "doublehigh": 0,
      "dual_class_name": "",
      "first_km": 70000,
      "id": "gkspecialscore20251040926",
      "info": "",
      "is_score_range": 2,
      "is_top": 2,
      "level2_name": "工学",
      "level3_name": "机械类",
      "local_batch_name": "本科批",
      "local_province_name": "河南",
      "local_type_name": "物理类",
      "max": 646,
      "min": 637,
      "min_range": "",
      "min_rank_range": "",
      "min_section": 14500,
      "name": "中国石油大学（北京）",
      "proscore": 427,
      "remark": "",
      "school_id": 832,
      "sg_fxk": "70000",
      "sg_info": "首选物理，再选化学",
      "sg_name": "（101）",
      "sg_sxk": "70001",
      "sg_type": 80003,
      "single": "",
      "sp_fxk": "",
      "sp_info": "",
      "sp_name": "机械类",
      "sp_scode": "",
      "sp_sxk": "",
      "sp_type": 0,
      "spe_id": 1345,
      "special_group": 503078,
      "special_id": 109430,
      "spname": "机械类",
      "year": 2025,
      "zslx_name": "-",
      "data_type": "special"
    },
    {
      "average": 637,
      "doublehigh": 0,
      "dual_class_name": "",
      "first_km": 70000,
      "id": "gkspecialscore20251040925",
      "info": "",
      "is_score_range": 2,
      "is_top": 2,
      "level2_name": "工学",
      "level3_name": "材料类",
      "local_batch_name": "本科批",
      "local_province_name": "河南",
      "local_type_name": "物理类",
      "max": 637,
      "min": 636,
      "min_range": "",
      "min_rank_range": "",
      "min_section": 15066,
      "name": "中国石油大学（北京）",
      "proscore": 427,
      "remark": "",
      "school_id": 832,
      "sg_fxk": "70000",
      "sg_info": "首选物理，再选化学",
      "sg_name": "（101）",
      "sg_sxk": "70001",
      "sg_type": 80003,
      "single": "",
      "sp_fxk": "",
      "sp_info": "",
      "sp_name": "材料科学与工程",
      "sp_scode": "",
      "sp_sxk": "",
      "sp_type": 0,
      "spe_id": 155,
      "special_group": 503078,
      "special_id": 37277,
      "spname": "材料科学与工程",
      "year": 2025,
      "zslx_name": "-",
      "data_type": "special"
    },
    {
      "average": 637,
      "doublehigh": 0,
      "dual_class_name": "",
      "first_km": 70000,
      "id": "gkspecialscore20251040924",
      "info": "",
      "is_score_range": 2,
      "is_top": 2,
      "level2_name": "工学",
      "level3_name": "矿业类",
      "local_batch_name": "本科批",
      "local_province_name": "河南",
      "local_type_name": "物理类",
      "max": 638,
      "min": 636,
      "min_range": "",
      "min_rank_range": "",
      "min_section": 15066,
      "name": "中国石油大学（北京）",
      "proscore": 427,
      "remark": "",
      "school_id": 832,
      "sg_fxk": "70000",
      "sg_info": "首选物理，再选化学",
      "sg_name": "（101）",
      "sg_sxk": "70001",
      "sg_type": 80003,
      "single": "",
      "sp_fxk": "",
      "sp_info": "",
      "sp_name": "碳储科学与工程",
      "sp_scode": "",
      "sp_sxk": "",
      "sp_type": 0,
      "spe_id": 9336,
      "special_group": 503078,
      "special_id": 1801709,
      "spname": "碳储科学与工程",
      "year": 2025,
      "zslx_name": "-",
      "data_type": "special"
    },
    {
      "average": 637,
      "doublehigh": 0,
      "dual_class_name": "",
      "first_km": 70000,
      "id": "gkspecialscore20251040923",
      "info": "",
      "is_score_range": 2,
      "is_top": 2,
      "level2_name": "工学",
      "level3_name": "能源动力类",
      "local_batch_name": "本科批",
      "local_province_name": "河南",
      "local_type_name": "物理类",
      "max": 638,
      "min": 635,
      "min_range": "",
      "min_rank_range": "",
      "min_section": 15727,
      "name": "中国石油大学（北京）",
      "proscore": 427,
      "remark": "",
      "school_id": 832,
      "sg_fxk": "70000",
      "sg_info": "首选物理，再选化学",
      "sg_name": "（101）",
      "sg_sxk": "70001",
      "sg_type": 80003,
      "single": "",
      "sp_fxk": "",
      "sp_info": "",
      "sp_name": "能源与动力工程",
      "sp_scode": "",
      "sp_sxk": "",
      "sp_type": 0,
      "spe_id": 163,
      "special_group": 503078,
      "special_id": 37303,
      "spname": "能源与动力工程",
      "year": 2025,
      "zslx_name": "-",
      "data_type": "special"
    },
    {
      "average": 637,
      "doublehigh": 0,
      "dual_class_name": "",
      "first_km": 70000,
      "id": "gkspecialscore20251040922",
      "info": "",
      "is_score_range": 2,
      "is_top": 2,
      "level2_name": "工学",
      "level3_name": "能源动力类",
      "local_batch_name": "本科批",
      "local_province_name": "河南",
      "local_type_name": "物理类",
      "max": 640,
      "min": 635,
      "min_range": "",
      "min_rank_range": "",
      "min_section": 15727,
      "name": "中国石油大学（北京）",
      "proscore": 427,
      "remark": "",
      "school_id": 832,
      "sg_fxk": "70000",
      "sg_info": "首选物理，再选化学",
      "sg_name": "（101）",
      "sg_sxk": "70001",
      "sg_type": 80003,
      "single": "",
      "sp_fxk": "",
      "sp_info": "",
      "sp_name": "储能科学与工程",
      "sp_scode": "",
      "sp_sxk": "",
      "sp_type": 0,
      "spe_id": 8689,
      "special_group": 503078,
      "special_id": 1500080,
      "spname": "储能科学与工程",
      "year": 2025,
      "zslx_name": "-",
      "data_type": "special"
    },
    {
      "average": 634,
      "doublehigh": 0,
      "dual_class_name": "",
      "first_km": 70000,
      "id": "gkspecialscore20251040921",
      "info": "",
      "is_score_range": 2,
      "is_top": 2,
      "level2_name": "工学",
      "level3_name": "矿业类",
      "local_batch_name": "本科批",
      "local_province_name": "河南",
      "local_type_name": "物理类",
      "max": 634,
      "min": 634,
      "min_range": "",
      "min_rank_range": "",
      "min_section": 16357,
      "name": "中国石油大学（北京）",
      "proscore": 427,
      "remark": "",
      "school_id": 832,
      "sg_fxk": "70000",
      "sg_info": "首选物理，再选化学",
      "sg_name": "（101）",
      "sg_sxk": "70001",
      "sg_type": 80003,
      "single": "",
      "sp_fxk": "",
      "sp_info": "",
      "sp_name": "海洋油气工程",
      "sp_scode": "",
      "sp_sxk": "",
      "sp_type": 0,
      "spe_id": 1181,
      "special_group": 503078,
      "special_id": 37269,
      "spname": "海洋油气工程",
      "year": 2025,
      "zslx_name": "-",
      "data_type": "special"
    },
    {
      "average": 634,
      "doublehigh": 0,
      "dual_class_name": "",
      "first_km": 70000,
      "id": "gkspecialscore20251040920",
      "info": "（智能探测）",
      "is_score_range": 2,
      "is_top": 2,
      "level2_name": "理学",
      "level3_name": "地球物理学类",
      "local_batch_name": "本科批",
      "local_province_name": "河南",
      "local_type_name": "物理类",
      "max": 635,
      "min": 634,
      "min_range": "",
      "min_rank_range": "",
      "min_section": 16357,
      "name": "中国石油大学（北京）",
      "proscore": 427,
      "remark": "",
      "school_id": 832,
      "sg_fxk": "70000",
      "sg_info": "首选物理，再选化学",
      "sg_name": "（101）",
      "sg_sxk": "70001",
      "sg_type": 80003,
      "single": "",
      "sp_fxk": "",
      "sp_info": "",
      "sp_name": "地球物理学",
      "sp_scode": "",
      "sp_sxk": "",
      "sp_type": 0,
      "spe_id": 132,
      "special_group": 503078,
      "special_id": 37295,
      "spname": "地球物理学（智能探测）",
      "year": 2025,
      "zslx_name": "-",
      "data_type": "special"
    },
    {
      "average": 636,
      "doublehigh": 0,
      "dual_class_name": "",
      "first_km": 70000,
      "id": "gkspecialscore20251040919",
      "info": "（油气与清洁地质能源）",
      "is_score_range": 2,
      "is_top": 2,
      "level2_name": "工学",
      "level3_name": "地质类",
      "local_batch_name": "本科批",
      "local_province_name": "河南",
      "local_type_name": "物理类",
      "max": 637,
      "min": 634,
      "min_range": "",
      "min_rank_range": "",
      "min_section": 16357,
      "name": "中国石油大学（北京）",
      "proscore": 427,
      "remark": "",
      "school_id": 832,
      "sg_fxk": "70000",
      "sg_info": "首选物理，再选化学",
      "sg_name": "（101）",
      "sg_sxk": "70001",
      "sg_type": 80003,
      "single": "",
      "sp_fxk": "",
      "sp_info": "",
      "sp_name": "资源勘查工程",
      "sp_scode": "",
      "sp_sxk": "",
      "sp_type": 0,
      "spe_id": 191,
      "special_group": 503078,
      "special_id": 37298,
      "spname": "资源勘查工程（油气与清洁地质能源）",
      "year": 2025,
      "zslx_name": "-",
      "data_type": "special"
    },
    {
      "average": 636,
      "doublehigh": 0,
      "dual_class_name": "",
      "first_km": 70000,
      "id": "gkspecialscore20251040918",
      "info": "",
      "is_score_range": 2,
      "is_top": 2,
      "level2_name": "工学",
      "level3_name": "矿业类",
      "local_batch_name": "本科批",
      "local_province_name": "河南",
      "local_type_name": "物理类",
      "max": 640,
      "min": 634,
      "min_range": "",
      "min_rank_range": "",
      "min_section": 16357,
      "name": "中国石油大学（北京）",
      "proscore": 427,
      "remark": "",
      "school_id": 832,
      "sg_fxk": "70000",
      "sg_info": "首选物理，再选化学",
      "sg_name": "（101）",
      "sg_sxk": "70001",
      "sg_type": 80003,
      "single": "",
      "sp_fxk": "",
      "sp_info": "",
      "sp_name": "油气储运工程",
      "sp_scode": "",
      "sp_sxk": "",
      "sp_type": 0,
      "spe_id": 195,
      "special_group": 503078,
      "special_id": 37276,
      "spname": "油气储运工程",
      "year": 2025,
      "zslx_name": "-",
      "data_type": "special"
    },
    {
      "average": 633,
      "doublehigh": 0,
      "dual_class_name": "",
      "first_km": 70000,
      "id": "gkspecialscore20251040917",
      "info": "",
      "is_score_range": 2,
      "is_top": 2,
      "level2_name": "工学",
      "level3_name": "环境科学与工程类",
      "local_batch_name": "本科批",
      "local_province_name": "河南",
      "local_type_name": "物理类",
      "max": 633,
      "min": 633,
      "min_range": "",
      "min_rank_range": "",
      "min_section": 16998,
      "name": "中国石油大学（北京）",
      "proscore": 427,
      "remark": "",
      "school_id": 832,
      "sg_fxk": "70000",
      "sg_info": "首选物理，再选化学",
      "sg_name": "（101）",
      "sg_sxk": "70001",
      "sg_type": 80003,
      "single": "",
      "sp_fxk": "",
      "sp_info": "",
      "sp_name": "环境工程",
      "sp_scode": "",
      "sp_sxk": "",
      "sp_type": 0,
      "spe_id": 232,
      "special_group": 503078,
      "special_id": 37284,
      "spname": "环境工程",
      "year": 2025,
      "zslx_name": "-",
      "data_type": "special"
    },
    {
      "average": 633,
      "doublehigh": 0,
      "dual_class_name": "",
      "first_km": 70000,
      "id": "gkspecialscore20251040916",
      "info": "",
      "is_score_range": 2,
      "is_top": 2,
      "level2_name": "理学",
      "level3_name": "化学类",
      "local_batch_name": "本科批",
      "local_province_name": "河南",
      "local_type_name": "物理类",
      "max": 633,
      "min": 633,
      "min_range": "",
      "min_rank_range": "",
      "min_section": 16998,
      "name": "中国石油大学（北京）",
      "proscore": 427,
      "remark": "",
      "school_id": 832,
      "sg_fxk": "70000",
      "sg_info": "首选物理，再选化学",
      "sg_name": "（101）",
      "sg_sxk": "70001",
      "sg_type": 80003,
      "single": "",
      "sp_fxk": "",
      "sp_info": "",
      "sp_name": "应用化学",
      "sp_scode": "",
      "sp_sxk": "",
      "sp_type": 0,
      "spe_id": 122,
      "special_group": 503078,
      "special_id": 37273,
      "spname": "应用化学",
      "year": 2025,
      "zslx_name": "-",
      "data_type": "special"
    },
    {
      "average": 633,
      "doublehigh": 0,
      "dual_class_name": "",
      "first_km": 70000,
      "id": "gkspecialscore20251040915",
      "info": "",
      "is_score_range": 2,
      "is_top": 2,
      "level2_name": "工学",
      "level3_name": "地质类",
      "local_batch_name": "本科批",
      "local_province_name": "河南",
      "local_type_name": "物理类",
      "max": 633,
      "min": 633,
      "min_range": "",
      "min_rank_range": "",
      "min_section": 16998,
      "name": "中国石油大学（北京）",
      "proscore": 427,
      "remark": "",
      "school_id": 832,
      "sg_fxk": "70000",
      "sg_info": "首选物理，再选化学",
      "sg_name": "（101）",
      "sg_sxk": "70001",
      "sg_type": 80003,
      "single": "",
      "sp_fxk": "",
      "sp_info": "",
      "sp_name": "勘查技术与工程",
      "sp_scode": "",
      "sp_sxk": "",
      "sp_type": 0,
      "spe_id": 190,
      "special_group": 503078,
      "special_id": 37275,
      "spname": "勘查技术与工程",
      "year": 2025,
      "zslx_name": "-",
      "data_type": "special"
    },
    {
      "average": 633,
      "doublehigh": 0,
      "dual_class_name": "",
      "first_km": 70000,
      "id": "gkspecialscore20251040914",
      "info": "",
      "is_score_range": 2,
      "is_top": 2,
      "level2_name": "工学",
      "level3_name": "机械类",
      "local_batch_name": "本科批",
      "local_province_name": "河南",
      "local_type_name": "物理类",
      "max": 634,
      "min": 633,
      "min_range": "",
      "min_rank_range": "",
      "min_section": 16998,
      "name": "中国石油大学（北京）",
      "proscore": 427,
      "remark": "",
      "school_id": 832,
      "sg_fxk": "70000",
      "sg_info": "首选物理，再选化学",
      "sg_name": "（101）",
      "sg_sxk": "70001",
      "sg_type": 80003,
      "single": "",
      "sp_fxk": "",
      "sp_info": "",
      "sp_name": "过程装备与控制工程",
      "sp_scode": "",
      "sp_sxk": "",
      "sp_type": 0,
      "spe_id": 151,
      "special_group": 503078,
      "special_id": 37279,
      "spname": "过程装备与控制工程",
      "year": 2025,
      "zslx_name": "-",
      "data_type": "special"
    },
    {
      "average": 634,
      "doublehigh": 0,
      "dual_class_name": "",
      "first_km": 70000,
      "id": "gkspecialscore20251040913",
      "info": "",
      "is_score_range": 2,
      "is_top": 2,
      "level2_name": "工学",
      "level3_name": "化工与制药类",
      "local_batch_name": "本科批",
      "local_province_name": "河南",
      "local_type_name": "物理类",
      "max": 634,
      "min": 633,
      "min_range": "",
      "min_rank_range": "",
      "min_section": 16998,
      "name": "中国石油大学（北京）",
      "proscore": 427,
      "remark": "",
      "school_id": 832,
      "sg_fxk": "70000",
      "sg_info": "首选物理，再选化学",
      "sg_name": "（101）",
      "sg_sxk": "70001",
      "sg_type": 80003,
      "single": "",
      "sp_fxk": "",
      "sp_info": "",
      "sp_name": "能源化学工程",
      "sp_scode": "",
      "sp_sxk": "",
      "sp_type": 0,
      "spe_id": 1177,
      "special_group": 503078,
      "special_id": 37316,
      "spname": "能源化学工程",
      "year": 2025,
      "zslx_name": "-",
      "data_type": "special"
    },
    {
      "average": 633,
      "doublehigh": 0,
      "dual_class_name": "",
      "first_km": 70000,
      "id": "gkspecialscore20251040912",
      "info": "",
      "is_score_range": 2,
      "is_top": 2,
      "level2_name": "工学",
      "level3_name": "安全科学与工程类",
      "local_batch_name": "本科批",
      "local_province_name": "河南",
      "local_type_name": "物理类",
      "max": 634,
      "min": 633,
      "min_range": "",
      "min_rank_range": "",
      "min_section": 16998,
      "name": "中国石油大学（北京）",
      "proscore": 427,
      "remark": "",
      "school_id": 832,
      "sg_fxk": "70000",
      "sg_info": "首选物理，再选化学",
      "sg_name": "（101）",
      "sg_sxk": "70001",
      "sg_type": 80003,
      "single": "",
      "sp_fxk": "",
      "sp_info": "",
      "sp_name": "安全工程",
      "sp_scode": "",
      "sp_sxk": "",
      "sp_type": 0,
      "spe_id": 244,
      "special_group": 503078,
      "special_id": 37307,
      "spname": "安全工程",
      "year": 2025,
      "zslx_name": "-",
      "data_type": "special"
    },
    {
      "average": 632,
      "doublehigh": 0,
      "dual_class_name": "",
      "first_km": 70000,
      "id": "gkspecialscore20251040911",
      "info": "",
      "is_score_range": 2,
      "is_top": 2,
      "level2_name": "理学",
      "level3_name": "数学类",
      "local_batch_name": "本科批",
      "local_province_name": "河南",
      "local_type_name": "物理类",
      "max": 633,
      "min": 632,
      "min_range": "",
      "min_rank_range": "",
      "min_section": 17632,
      "name": "中国石油大学（北京）",
      "proscore": 427,
      "remark": "",
      "school_id": 832,
      "sg_fxk": "70000",
      "sg_info": "首选物理，再选化学",
      "sg_name": "（101）",
      "sg_sxk": "70001",
      "sg_type": 80003,
      "single": "",
      "sp_fxk": "",
      "sp_info": "",
      "sp_name": "数学与应用数学",
      "sp_scode": "",
      "sp_sxk": "",
      "sp_type": 0,
      "spe_id": 116,
      "special_group": 503078,
      "special_id": 37271,
      "spname": "数学与应用数学",
      "year": 2025,
      "zslx_name": "-",
      "data_type": "special"
    },
    {
      "average": 633,
      "doublehigh": 0,
      "dual_class_name": "",
      "first_km": 70000,
      "id": "gkspecialscore20251040910",
      "info": "",
      "is_score_range": 2,
      "is_top": 2,
      "level2_name": "工学",
      "level3_name": "化工与制药类",
      "local_batch_name": "本科批",
      "local_province_name": "河南",
      "local_type_name": "物理类",
      "max": 634,
      "min": 632,
      "min_range": "",
      "min_rank_range": "",
      "min_section": 17632,
      "name": "中国石油大学（北京）",
      "proscore": 427,
      "remark": "",
      "school_id": 832,
      "sg_fxk": "70000",
      "sg_info": "首选物理，再选化学",
      "sg_name": "（101）",
      "sg_sxk": "70001",
      "sg_type": 80003,
      "single": "",
      "sp_fxk": "",
      "sp_info": "",
      "sp_name": "化学工程与工艺",
      "sp_scode": "",
      "sp_sxk": "",
      "sp_type": 0,
      "spe_id": 187,
      "special_group": 503078,
      "special_id": 37267,
      "spname": "化学工程与工艺",
      "year": 2025,
      "zslx_name": "-",
      "data_type": "special"
    },
    {
      "average": 633,
      "doublehigh": 0,
      "dual_class_name": "",
      "first_km": 70000,
      "id": "gkspecialscore20251040909",
      "info": "（新能源工程双学士学位）",
      "is_score_range": 2,
      "is_top": 2,
      "level2_name": "经济学",
      "level3_name": "经济学类",
      "local_batch_name": "本科批",
      "local_province_name": "河南",
      "local_type_name": "物理类",
      "max": 636,
      "min": 631,
      "min_range": "",
      "min_rank_range": "",
      "min_section": 18242,
      "name": "中国石油大学（北京）",
      "proscore": 427,
      "remark": "",
      "school_id": 832,
      "sg_fxk": "70000",
      "sg_info": "首选物理，再选不限",
      "sg_name": "（102）",
      "sg_sxk": "70008",
      "sg_type": 80001,
      "single": "",
      "sp_fxk": "",
      "sp_info": "",
      "sp_name": "能源经济",
      "sp_scode": "",
      "sp_sxk": "",
      "sp_type": 0,
      "spe_id": 1102,
      "special_group": 503091,
      "special_id": 37317,
      "spname": "能源经济（新能源工程双学士学位）",
      "year": 2025,
      "zslx_name": "-",
      "data_type": "special"
    },
    {
      "average": 627,
      "doublehigh": 0,
      "dual_class_name": "",
      "first_km": 70000,
      "id": "gkspecialscore20251040908",
      "info": "",
      "is_score_range": 2,
      "is_top": 2,
      "level2_name": "经济学",
      "level3_name": "经济学类",
      "local_batch_name": "本科批",
      "local_province_name": "河南",
      "local_type_name": "物理类",
      "max": 627,
      "min": 627,
      "min_range": "",
      "min_rank_range": "",
      "min_section": 20939,
      "name": "中国石油大学（北京）",
      "proscore": 427,
      "remark": "",
      "school_id": 832,
      "sg_fxk": "70000",
      "sg_info": "首选物理，再选不限",
      "sg_name": "（102）",
      "sg_sxk": "70008",
      "sg_type": 80001,
      "single": "",
      "sp_fxk": "",
      "sp_info": "",
      "sp_name": "经济学类",
      "sp_scode": "",
      "sp_sxk": "",
      "sp_type": 0,
      "spe_id": 1316,
      "special_group": 503091,
      "special_id": 109417,
      "spname": "经济学类",
      "year": 2025,
      "zslx_name": "-",
      "data_type": "special"
    },
    {
      "average": 630,
      "doublehigh": 0,
      "dual_class_name": "",
      "first_km": 70000,
      "id": "gkspecialscore20251040907",
      "info": "",
      "is_score_range": 2,
      "is_top": 2,
      "level2_name": "管理学",
      "level3_name": "管理科学与工程类",
      "local_batch_name": "本科批",
      "local_province_name": "河南",
      "local_type_name": "物理类",
      "max": 632,
      "min": 627,
      "min_range": "",
      "min_rank_range": "",
      "min_section": 20939,
      "name": "中国石油大学（北京）",
      "proscore": 427,
      "remark": "",
      "school_id": 832,
      "sg_fxk": "70000",
      "sg_info": "首选物理，再选不限",
      "sg_name": "（102）",
      "sg_sxk": "70008",
      "sg_type": 80001,
      "single": "",
      "sp_fxk": "",
      "sp_info": "",
      "sp_name": "信息管理与信息系统",
      "sp_scode": "",
      "sp_sxk": "",
      "sp_type": 0,
      "spe_id": 293,
      "special_group": 503091,
      "special_id": 37285,
      "spname": "信息管理与信息系统",
      "year": 2025,
      "zslx_name": "-",
      "data_type": "special"
    },
    {
      "average": 626,
      "doublehigh": 0,
      "dual_class_name": "",
      "first_km": 70000,
      "id": "gkspecialscore20251040906",
      "info": "",
      "is_score_range": 2,
      "is_top": 2,
      "level2_name": "管理学",
      "level3_name": "工商管理类",
      "local_batch_name": "本科批",
      "local_province_name": "河南",
      "local_type_name": "物理类",
      "max": 628,
      "min": 625,
      "min_range": "",
      "min_rank_range": "",
      "min_section": 22450,
      "name": "中国石油大学（北京）",
      "proscore": 427,
      "remark": "",
      "school_id": 832,
      "sg_fxk": "70000",
      "sg_info": "首选物理，再选不限",
      "sg_name": "（102）",
      "sg_sxk": "70008",
      "sg_type": 80001,
      "single": "",
      "sp_fxk": "",
      "sp_info": "",
      "sp_name": "工商管理类",
      "sp_scode": "",
      "sp_sxk": "",
      "sp_type": 0,
      "spe_id": 1394,
      "special_group": 503091,
      "special_id": 109418,
      "spname": "工商管理类",
      "year": 2025,
      "zslx_name": "-",
      "data_type": "special"
    },
    {
      "average": 618,
      "doublehigh": 0,
      "dual_class_name": "",
      "first_km": 70004,
      "id": "gkspecialscore20251040935",
      "info": "",
      "is_score_range": 2,
      "is_top": 2,
      "level2_name": "法学",
      "level3_name": "马克思主义理论类",
      "local_batch_name": "本科批",
      "local_province_name": "河南",
      "local_type_name": "历史类",
      "max": 619,
      "min": 615,
      "min_range": "",
      "min_rank_range": "",
      "min_section": 3337,
      "name": "中国石油大学（北京）",
      "proscore": 471,
      "remark": "",
      "school_id": 832,
      "sg_fxk": "70004",
      "sg_info": "首选历史，再选思想政治",
      "sg_name": "（103）",
      "sg_sxk": "70003",
      "sg_type": 80003,
      "single": "",
      "sp_fxk": "",
      "sp_info": "",
      "sp_name": "思想政治教育",
      "sp_scode": "",
      "sp_sxk": "",
      "sp_type": 0,
      "spe_id": 23,
      "special_group": 503098,
      "special_id": 1129615,
      "spname": "思想政治教育",
      "year": 2025,
      "zslx_name": "-",
      "data_type": "special"
    },
    {
      "average": 615,
      "doublehigh": 0,
      "dual_class_name": "",
      "first_km": 70004,
      "id": "gkspecialscore20251040934",
      "info": "（全球能源治理）",
      "is_score_range": 2,
      "is_top": 2,
      "level2_name": "文学",
      "level3_name": "外国语言文学类",
      "local_batch_name": "本科批",
      "local_province_name": "河南",
      "local_type_name": "历史类",
      "max": 616,
      "min": 613,
      "min_range": "",
      "min_rank_range": "",
      "min_section": 3645,
      "name": "中国石油大学（北京）",
      "proscore": 471,
      "remark": "",
      "school_id": 832,
      "sg_fxk": "70004",
      "sg_info": "首选历史，再选不限",
      "sg_name": "（104）",
      "sg_sxk": "70008",
      "sg_type": 80001,
      "single": "",
      "sp_fxk": "",
      "sp_info": "",
      "sp_name": "英语",
      "sp_scode": "",
      "sp_sxk": "",
      "sp_type": 0,
      "spe_id": 45,
      "special_group": 503099,
      "special_id": 37290,
      "spname": "英语（全球能源治理）",
      "year": 2025,
      "zslx_name": "-",
      "data_type": "special"
    }
  ]
}